Workbook

Sheet Solicitud
A1: COOPERATIVA MIXTA DE FARMACÉUTICOS DE HONDURAS (COMIFARH)
A3: SOLICITUD DE PRÉSTAMO AUTOMÁTICO
A5: RESUMEN DEL CRÉDITO
A6: Total aportaciones (L) | B6: =B33 -> 0
A7: Monto máximo (90%) | B7: =B34 -> 0
A8: Monto solicitado (L) | B8: =B35 -> 0
A9: Plazo (meses) | B9: =B36 -> 0
A10: Tasa anual | B10: ='Análisis de Crédito'!B5 -> 0.12
A11: Cuota estimada | B11: =Amortización!F12 -> 0
A12: Desembolso | B12: =B35 -> 0
A14: I. DATOS GENERALES DEL SOLICITANTE
A15: Fecha de solicitud
A16: Número de asociado
A17: Nombre completo
A18: Tipo de identificación
A19: Número de identificación
A20: Fecha de nacimiento
A21: Estado civil
A22: Dirección completa
A23: Departamento
A24: Municipio
A25: Teléfono
... A33: Total de aportaciones (L) (Obligatorias+Voluntarias)
A34: Monto máximo permitido (90% aportaciones) (L) | B34: =B33*0.9 -> 0
A35: Monto solicitado (L)
A36: Plazo solicitado (meses)
A37: Aportación mensual vigente (L)
A38: Forma de pago
A39: Destino del crédito
A40: Descripción del destino
A41: Fecha de primer pago (opcional)
A42: IV. REFERENCIAS PERSONALES (No convivientes)
A43: Referencia 1 - Nombre
A44: Referencia 1 - Parentesco
A45: Referencia 1 - Teléfono
A46: Referencia 2 - Nombre
... A64: CHECKLIST (marque): ☐ Identidad ☐ Pagaré ☐ Estado de aportaciones ☐ Otros

Sheet Listas
A1: tipo_id | B1: DNI | C1: RTN | D1: Pasaporte
A2: estado_civil | B2: Soltero(a) | C2: Casado(a) | D2: Unión libre | E2: Divorciado(a) | F2: Viudo(a)
A3: cond_laboral | B3: Empleado(a) público | C3: Empleado(a) privado | D3: Negocio propio | E3: Jubilado(a)
A4: plazo | B4: 1 | C4: 2 | D4: 3 | E4: 4 | F4: 5 | G4: 6 | H4: 7 | I4: 8 | J4: 9 | K4: 10 | L4: 11 | M4: 12
A5: forma_pago | B5: Deducción por planilla | C5: Pago en ventanilla | D5: Transferencia bancaria
A6: destino | B6: Consumo personal | C6: Educación | D6: Salud | E6: Otro
A7: parentesco | B7: Familiar | C7: Amistad
A8: recomendacion | B8: Aprobado | C8: Condicionado | D8: Rechazado
A9: departamento | B9: Atlántida | C9: Choluteca | D9: Colón | E9: Comayagua | F9: Copán | G9: Cortés | H9: El Paraíso | I9: Francisco Morazán | J9: Gracias a Dios | K9: Intibucá | L9: Islas de la Bahía | M9: La Paz | N9: Lempira | O9: Ocotepeque | P9: Olancho | Q9: Santa Bárbara | R9: Valle | S9: Yoro

Sheet Análisis de Crédito
A1: ANÁLISIS DE CRÉDITO – PRÉSTAMO AUTOMÁTICO (COMIFARH)
A4: 1) PARÁMETROS
A5: Tasa anual préstamo automático | B5: 0.12 | D5: Automático 12% anual
A6: Retención a aportaciones | B6: 0.05 | D6: Editable
A7: Gastos operativos | B7: 0.03 | D7: Editable
A8: Cobertura máxima sobre aportaciones | B8: 0.9 | D8: No excede 90% aportaciones
A9: Plazo máximo (meses) | B9: 12 | D9: Plazo máx. 12 meses
A11: 2) DATOS (desde Solicitud)
A12: Ingreso mensual neto (L) | B12: =Solicitud!B31 -> 0
A13: Total aportaciones (L) | B13: =Solicitud!B33 -> 0
A14: Monto solicitado (L) | B14: =Solicitud!B35 -> 0
A15: Plazo solicitado (meses) | B15: =Solicitud!B36 -> 0
A16: Aportación mensual vigente (L) | B16: =Solicitud!B37 -> 0
A18: 3) VALIDACIONES Y CÁLCULO
A19: Monto máximo permitido (L) | B19: =B13*$B$8 -> 0
A20: Tasa mensual | B20: =$B$5/12 -> 0.01
A21: Cuota mensual estimada (L) | B21: =-PMT(B20,B15,B14) -> #NUM!
A22: Cuota total (incluye aportación) (L) | B22: =B21+B16 -> #NUM!
A23: Retención 5% (L) | B23: =B14*B6 -> 0
A24: Gastos operativos 3% (L) | B24: =B14*B7 -> 0
A25: Desembolso (L) | B25: =B14-B23-B24 -> 0
A26: Cumple monto ≤ máximo | B26: =IF(B14<=B19,"SÍ","NO") -> SÍ
A27: Cumple plazo ≤ máximo | B27: =IF(B15<=$B$9,"SÍ","NO") -> SÍ
A29: 4) DICTAMEN
A30: Dictamen del analista | D30: Observaciones
A31: Recomendación final | B31: =IF(AND(B26="SÍ",B27="SÍ"),"APROBABLE","REVISAR / CONDICIONAR") -> APROBABLE

Sheet Amortización
A1: TABLA DE AMORTIZACIÓN – PRÉSTAMO AUTOMÁTICO
A3: CLIENTE: | C3: =[1]Solicitud!B16 -> 0
A4: Gastos Operativos | C4: 0.03 | D4: =SUM(C12*C4) -> 0
A5: Aportaciones | C5: 0.05 | D5: =SUM(C12*C5) -> 0
A6: Tasa de Seguridad
A7: Cancelación Préstamo | D7: 0
A8: Total deducciones | D8: =SUM(D4:D7) -> 0
A9: Total a desembolsar | D9: =SUM(C12-D8) -> 0 | E9: FECHAS: | F9: Inicio | G9: Final
C11: MONTO | D11: PLAZO | E11: TASA | F11: CUOTA | G11: Cuota+Aport
B12: Principal | C12: =Solicitud!B35 -> 0 | D12: ='Análisis de Crédito'!B9 -> 12 | E12: ='Análisis de Crédito'!B5 -> 0.12 | F12: =C12/((1-((1+(E12/12))^-D12))/(E12/12)) -> 0 | G12: =F12+'Análisis de Crédito'!B16 -> 0
B13: Plazo (meses)
B14: Tasa anual
B15: Cuota (fórmula)
B16: Fecha 1er pago (opcional) | C16: =Solicitud!B41 -> 0
A18: # | B18: Fecha | C18: Saldo inicial | D18: Cuota | E18: Interés | F18: Capital | G18: Saldo final
A19: =IF(1<=$D$12,1,"") -> 1 | B19: =IF(1<=$D$12,IF($C$16="","",EDATE($C$16,1-1)),"") -> 0 | C19: =IF(1<=$D$12,IF(1=1,$C$12,G18),"") -> 0 | D19: =IF(1<=$D$12,$F$12,"") -> 0 | E19: =IF(1<=$D$12,C19*($E$12/12),"") -> 0 | F19: =IF(1<=$D$12,D19-E19,"") -> 0 | G19: =IF(1<=$D$12,MAX(0,C19-F19),"") -> 0
A20: =IF(2<=$D$12,2,"") -> 2 | B20: =IF(2<=$D$12,IF($C$16="","",EDATE($C$16,2-1)),"") -> 31 | C20: =IF(2<=$D$12,IF(2=1,$C$12,G19),"") -> 0 | D20: =IF(2<=$D$12,$F$12,"") -> 0 | E20: =IF(2<=$D$12,C20*($E$12/12),"") -> 0 | F20: =IF(2<=$D$12,D20-E20,"") -> 0 | G20: =IF(2<=$D$12,MAX(0,C20-F20),"") -> 0
A21: =IF(3<=$D$12,3,"") -> 3 | B21: =IF(3<=$D$12,IF($C$16="","",EDATE($C$16,3-1)),"") -> 60 | C21: =IF(3<=$D$12,IF(3=1,$C$12,G20),"") -> 0 | D21: =IF(3<=$D$12,$F$12,"") -> 0 | E21: =IF(3<=$D$12,C21*($E$12/12),"") -> 0 | F21: =IF(3<=$D$12,D21-E21,"") -> 0 | G21: =IF(3<=$D$12,MAX(0,C21-F21),"") -> 0
A22: =IF(4<=$D$12,4,"") -> 4 | B22: =IF(4<=$D$12,IF($C$16="","",EDATE($C$16,4-1)),"") -> 91 | C22: =IF(4<=$D$12,IF(4=1,$C$12,G21),"") -> 0 | D22: =IF(4<=$D$12,$F$12,"") -> 0 | E22: =IF(4<=$D$12,C22*($E$12/12),"") -> 0 | F22: =IF(4<=$D$12,D22-E22,"") -> 0 | G22: =IF(4<=$D$12,MAX(0,C22-F22),"") -> 0
A23: =IF(5<=$D$12,5,"") -> 5 | B23: =IF(5<=$D$12,IF($C$16="","",EDATE($C$16,5-1)),"") -> 121 | C23: =IF(5<=$D$12,IF(5=1,$C$12,G22),"") -> 0 | D23: =IF(5<=$D$12,$F$12,"") -> 0 | E23: =IF(5<=$D$12,C23*($E$12/12),"") -> 0 | F23: =IF(5<=$D$12,D23-E23,"") -> 0 | G23: =IF(5<=$D$12,MAX(0,C23-F23),"") -> 0
A24: =IF(6<=$D$12,6,"") -> 6 | B24: =IF(6<=$D$12,IF($C$16="","",EDATE($C$16,6-1)),"") -> 152 | C24: =IF(6<=$D$12,IF(6=1,$C$12,G23),"") -> 0 | D24: =IF(6<=$D$12,$F$12,"") -> 0 | E24: =IF(6<=$D$12,C24*($E$12/12),"") -> 0 | F24: =IF(6<=$D$12,D24-E24,"") -> 0 | G24: =IF(6<=$D$12,MAX(0,C24-F24),"") -> 0
A25: =IF(7<=$D$12,7,"") -> 7 | B25: =IF(7<=$D$12,IF($C$16="","",EDATE($C$16,7-1)),"") -> 182 | C25: =IF(7<=$D$12,IF(7=1,$C$12,G24),"") -> 0 | D25: =IF(7<=$D$12,$F$12,"") -> 0 | E25: =IF(7<=$D$12,C25*($E$12/12),"") -> 0 | F25: =IF(7<=$D$12,D25-E25,"") -> 0 | G25: =IF(7<=$D$12,MAX(0,C25-F25),"") -> 0
A26: =IF(8<=$D$12,8,"") -> 8 | B26: =IF(8<=$D$12,IF($C$16="","",EDATE($C$16,8-1)),"") -> 213 | C26: =IF(8<=$D$12,IF(8=1,$C$12,G25),"") -> 0 | D26: =IF(8<=$D$12,$F$12,"") -> 0 | E26: =IF(8<=$D$12,C26*($E$12/12),"") -> 0 | F26: =IF(8<=$D$12,D26-E26,"") -> 0 | G26: =IF(8<=$D$12,MAX(0,C26-F26),"") -> 0
A27: =IF(9<=$D$12,9,"") -> 9 | B27: =IF(9<=$D$12,IF($C$16="","",EDATE($C$16,9-1)),"") -> 244 | C27: =IF(9<=$D$12,IF(9=1,$C$12,G26),"") -> 0 | D27: =IF(9<=$D$12,$F$12,"") -> 0 | E27: =IF(9<=$D$12,C27*($E$12/12),"") -> 0 | F27: =IF(9<=$D$12,D27-E27,"") -> 0 | G27: =IF(9<=$D$12,MAX(0,C27-F27),"") -> 0
A28: =IF(10<=$D$12,10,"") -> 10 | B28: =IF(10<=$D$12,IF($C$16="","",EDATE($C$16,10-1)),"") -> 274 | C28: =IF(10<=$D$12,IF(10=1,$C$12,G27),"") -> 0 | D28: =IF(10<=$D$12,$F$12,"") -> 0 | E28: =IF(10<=$D$12,C28*($E$12/12),"") -> 0 | F28: =IF(10<=$D$12,D28-E28,"") -> 0 | G28: =IF(10<=$D$12,MAX(0,C28-F28),"") -> 0
A29: =IF(11<=$D$12,11,"") -> 11 | B29: =IF(11<=$D$12,IF($C$16="","",EDATE($C$16,11-1)),"") -> 305 | C29: =IF(11<=$D$12,IF(11=1,$C$12,G28),"") -> 0 | D29: =IF(11<=$D$12,$F$12,"") -> 0 | E29: =IF(11<=$D$12,C29*($E$12/12),"") -> 0 | F29: =IF(11<=$D$12,D29-E29,"") -> 0 | G29: =IF(11<=$D$12,MAX(0,C29-F29),"") -> 0
A30: =IF(12<=$D$12,12,"") -> 12 | B30: =IF(12<=$D$12,IF($C$16="","",EDATE($C$16,12-1)),"") -> 335 | C30: =IF(12<=$D$12,IF(12=1,$C$12,G29),"") -> 0 | D30: =IF(12<=$D$12,$F$12,"") -> 0 | E30: =IF(12<=$D$12,C30*($E$12/12),"") -> 0 | F30: =IF(12<=$D$12,D30-E30,"") -> 0 | G30: =IF(12<=$D$12,MAX(0,C30-F30),"") -> 0
