Workbook

Sheet Solicitud
A1: COOPERATIVA MIXTA DE FARMACÉUTICOS DE HONDURAS (COMIFARH)
A3: SOLICITUD DE PRÉSTAMO HIPOTECARIO
A5: RESUMEN DEL CRÉDITO
A6: Valor avalúo (L) | B6: =B48 -> 0
A7: Monto máximo (80%) | B7: =B49 -> 0
A8: Monto solicitado (L) | B8: =B33 -> 0
A9: Plazo (meses) | B9: =B34 -> 0
A10: Tasa anual | B10: ='Análisis de Crédito'!B5 -> 0.1
A11: Cuota estimada | B11: =Amortización!F12 -> 0
A12: Relación LTV | B12: =IF(B6=0,0,B8/B6) -> 0
A14: I. DATOS GENERALES DEL SOLICITANTE
A15: Fecha de solicitud
A16: Número de asociado
A17: Nombre completo
A18: Tipo de identificación
A19: Número de identificación
A20: Fecha de nacimiento
A21: Estado civil
A22: Dirección completa
A23: Departamento
A24: Municipio
A25: Teléfono
... A48: Valor de avalúo (L)
A49: Monto máximo permitido (80% avalúo) (L) | B49: =B48*0.8 -> 0
A50: ¿Seguro de deuda endosado a COMIFARH?
A51: ¿Seguro del bien endosado a COMIFARH?
A52: No. póliza seguro deuda
A53: No. póliza seguro bien
A54: Aportación mensual vigente (L)
A55: V. REFERENCIAS PERSONALES (No convivientes)
A56: Referencia 1 - Nombre
A57: Referencia 1 - Parentesco
A58: Referencia 1 - Teléfono
A59: Referencia 2 - Nombre
A60: Referencia 2 - Parentesco
A61: Referencia 2 - Teléfono
... A77: CHECKLIST (marque): ☐ Identidad ☐ RTN (si aplica) ☐ Escritura ☐ Avalúo ☐ Certificación libertad de gravamen ☐ Seguro de deuda endosado ☐ Seguro del bien endosado ☐ Otros

Sheet Listas
A1: tipo_id | B1: DNI | C1: RTN | D1: Pasaporte
A2: estado_civil | B2: Soltero(a) | C2: Casado(a) | D2: Unión libre | E2: Divorciado(a) | F2: Viudo(a)
A3: cond_laboral | B3: Empleado(a) público | C3: Empleado(a) privado | D3: Negocio propio | E3: Jubilado(a)
A4: plazo | B4: 12 | C4: 24 | D4: 36 | E4: 48 | F4: 60 | G4: 72 | H4: 84 | I4: 96 | J4: 108 | K4: 120
A5: forma_pago | B5: Deducción por planilla | C5: Pago en ventanilla | D5: Transferencia bancaria
A6: destino | B6: Vivienda | C6: Mejoras/Remodelación | D6: Compra de lote | E6: Consolidación | F6: Otro
A7: parentesco | B7: Familiar | C7: Amistad
A8: recomendacion | B8: Aprobado | C8: Condicionado | D8: Rechazado
A9: si_no | B9: Sí | C9: No
A10: tipo_inmueble | B10: Casa | C10: Apartamento | D10: Terreno | E10: Local comercial | F10: Otro
A11: departamento | B11: Atlántida | C11: Choluteca | D11: Colón | E11: Comayagua | F11: Copán | G11: Cortés | H11: El Paraíso | I11: Francisco Morazán | J11: Gracias a Dios | K11: Intibucá | L11: Islas de la Bahía | M11: La Paz | N11: Lempira | O11: Ocotepeque | P11: Olancho | Q11: Santa Bárbara | R11: Valle | S11: Yoro

Sheet Análisis de Crédito
A1: ANÁLISIS DE CRÉDITO – PRÉSTAMO HIPOTECARIO (COMIFARH)
A4: 1) PARÁMETROS
A5: Tasa anual hipotecario | B5: 0.1 | D5: Referencia: Hipotecario 10% anual
A6: LTV máximo (sobre avalúo) | B6: 0.8 | D6: Referencia: se presta 80% del avalúo
A7: Plazo máximo (meses) | B7: 120 | D7: Referencia: plazo máx. 120 meses
A8: Máx. deuda/ingreso neto | B8: 0.3 | D8: Política general: deuda ≤ 30% ingreso neto
A10: 2) DATOS (desde Solicitud)
A11: Ingreso mensual neto (L) | B11: =Solicitud!B31 -> 0
A12: Valor de avalúo (L) | B12: =Solicitud!B48 -> 0
A13: Monto solicitado (L) | B13: =Solicitud!B33 -> 0
A14: Plazo solicitado (meses) | B14: =Solicitud!B34 -> 0
A15: Aportación mensual vigente (L) | B15: =Solicitud!B54 -> 0
A17: 3) VALIDACIONES Y CÁLCULO
A18: Monto máximo permitido (L) | B18: =B12*$B$6 -> 0
A19: Tasa mensual | B19: =$B$5/12 -> 0.0083333333
A20: Cuota mensual estimada (L) | B20: =-PMT(B19,B14,B13) -> #NUM!
A21: Cuota total (incluye aportación) (L) | B21: =B20+B15 -> #NUM!
A22: Relación cuota/ingreso (%) | B22: =B20/B11 -> #NUM!
A23: Cumple monto ≤ máximo | B23: =IF(B13<=B18,"SÍ","NO") -> SÍ
A24: Cumple plazo ≤ máximo | B24: =IF(B14<=$B$7,"SÍ","NO") -> SÍ
A25: Cumple cuota/ingreso ≤ límite | B25: =IF(B22<=$B$8,"SÍ","NO") -> #NUM!
A27: 4) DICTAMEN
A28: Dictamen del analista | D28: Observaciones y condiciones
A29: Recomendación final | B29: =IF(AND(B23="SÍ",B24="SÍ",B25="SÍ"),"APROBABLE","REVISAR / CONDICIONAR") -> #NUM!

Sheet Amortización
A1: TABLA DE AMORTIZACIÓN – PRÉSTAMO HIPOTECARIO
A3: CLIENTE: | C3: =Solicitud!B17 -> 0
A4: Gastos Operativos | C4: 0.03 | D4: =SUM(C12*C4) -> 0
A5: Aportaciones | C5: 0.05 | D5: =SUM(C12*C5) -> 0
A6: Tasa de Seguridad
A7: Cancelación Préstamo | D7: 0
A8: Total deducciones | D8: =SUM(D4:D7) -> 0
A9: Total a desembolsar | D9: =SUM(C12-D8) -> 0 | E9: FECHAS: | F9: Inicio | G9: Final
F10: 46142 | G10: 49795
C11: MONTO | D11: PLAZO | E11: TASA | F11: CUOTA | G11: Cuota+Aport
A12: Principal | C12: ='Análisis de Crédito'!B13 -> 0 | D12: ='Análisis de Crédito'!B7 -> 120 | E12: ='Análisis de Crédito'!B5 -> 0.1 | F12: =C12/((1-((1+(E12/12))^-D12))/(E12/12)) -> 0 | G12: =F12+Solicitud!B54 -> 0
A13: Plazo (meses)
A14: Tasa anual
A15: Cuota (fórmula)
A16: Fecha 1er pago | C16: =Solicitud!B38 -> 0
A18: # | B18: Fecha | C18: Saldo inicial | D18: Cuota | E18: Interés | F18: Capital | G18: Saldo final
A19: =IF(1<=$D$12,1,"") -> 1 | B19: =IF(1<=$D$12,IF($C$16="","",EDATE($C$16,1-1)),"") -> 0 | C19: =IF(1<=$D$12,IF(1=1,$C$12,G18),"") -> 0 | D19: =IF(1<=$D$12,$F$12,"") -> 0 | E19: =IF(1<=$D$12,C19*($E$12/12),"") -> 0 | F19: =IF(1<=$D$12,D19-E19,"") -> 0 | G19: =IF(1<=$D$12,MAX(0,C19-F19),"") -> 0
A20: =IF(2<=$D$12,2,"") -> 2 | B20: =IF(2<=$D$12,IF($C$16="","",EDATE($C$16,2-1)),"") -> 31 | C20: =IF(2<=$D$12,IF(2=1,$C$12,G19),"") -> 0 | D20: =IF(2<=$D$12,$F$12,"") -> 0 | E20: =IF(2<=$D$12,C20*($E$12/12),"") -> 0 | F20: =IF(2<=$D$12,D20-E20,"") -> 0 | G20: =IF(2<=$D$12,MAX(0,C20-F20),"") -> 0
A21: =IF(3<=$D$12,3,"") -> 3 | B21: =IF(3<=$D$12,IF($C$16="","",EDATE($C$16,3-1)),"") -> 60 | C21: =IF(3<=$D$12,IF(3=1,$C$12,G20),"") -> 0 | D21: =IF(3<=$D$12,$F$12,"") -> 0 | E21: =IF(3<=$D$12,C21*($E$12/12),"") -> 0 | F21: =IF(3<=$D$12,D21-E21,"") -> 0 | G21: =IF(3<=$D$12,MAX(0,C21-F21),"") -> 0
A22: =IF(4<=$D$12,4,"") -> 4 | B22: =IF(4<=$D$12,IF($C$16="","",EDATE($C$16,4-1)),"") -> 91 | C22: =IF(4<=$D$12,IF(4=1,$C$12,G21),"") -> 0 | D22: =IF(4<=$D$12,$F$12,"") -> 0 | E22: =IF(4<=$D$12,C22*($E$12/12),"") -> 0 | F22: =IF(4<=$D$12,D22-E22,"") -> 0 | G22: =IF(4<=$D$12,MAX(0,C22-F22),"") -> 0
A23: =IF(5<=$D$12,5,"") -> 5 | B23: =IF(5<=$D$12,IF($C$16="","",EDATE($C$16,5-1)),"") -> 121 | C23: =IF(5<=$D$12,IF(5=1,$C$12,G22),"") -> 0 | D23: =IF(5<=$D$12,$F$12,"") -> 0 | E23: =IF(5<=$D$12,C23*($E$12/12),"") -> 0 | F23: =IF(5<=$D$12,D23-E23,"") -> 0 | G23: =IF(5<=$D$12,MAX(0,C23-F23),"") -> 0
A24: =IF(6<=$D$12,6,"") -> 6 | B24: =IF(6<=$D$12,IF($C$16="","",EDATE($C$16,6-1)),"") -> 152 | C24: =IF(6<=$D$12,IF(6=1,$C$12,G23),"") -> 0 | D24: =IF(6<=$D$12,$F$12,"") -> 0 | E24: =IF(6<=$D$12,C24*($E$12/12),"") -> 0 | F24: =IF(6<=$D$12,D24-E24,"") -> 0 | G24: =IF(6<=$D$12,MAX(0,C24-F24),"") -> 0
A25: =IF(7<=$D$12,7,"") -> 7 | B25: =IF(7<=$D$12,IF($C$16="","",EDATE($C$16,7-1)),"") -> 182 | C25: =IF(7<=$D$12,IF(7=1,$C$12,G24),"") -> 0 | D25: =IF(7<=$D$12,$F$12,"") -> 0 | E25: =IF(7<=$D$12,C25*($E$12/12),"") -> 0 | F25: =IF(7<=$D$12,D25-E25,"") -> 0 | G25: =IF(7<=$D$12,MAX(0,C25-F25),"") -> 0
A26: =IF(8<=$D$12,8,"") -> 8 | B26: =IF(8<=$D$12,IF($C$16="","",EDATE($C$16,8-1)),"") -> 213 | C26: =IF(8<=$D$12,IF(8=1,$C$12,G25),"") -> 0 | D26: =IF(8<=$D$12,$F$12,"") -> 0 | E26: =IF(8<=$D$12,C26*($E$12/12),"") -> 0 | F26: =IF(8<=$D$12,D26-E26,"") -> 0 | G26: =IF(8<=$D$12,MAX(0,C26-F26),"") -> 0
A27: =IF(9<=$D$12,9,"") -> 9 | B27: =IF(9<=$D$12,IF($C$16="","",EDATE($C$16,9-1)),"") -> 244 | C27: =IF(9<=$D$12,IF(9=1,$C$12,G26),"") -> 0 | D27: =IF(9<=$D$12,$F$12,"") -> 0 | E27: =IF(9<=$D$12,C27*($E$12/12),"") -> 0 | F27: =IF(9<=$D$12,D27-E27,"") -> 0 | G27: =IF(9<=$D$12,MAX(0,C27-F27),"") -> 0
A28: =IF(10<=$D$12,10,"") -> 10 | B28: =IF(10<=$D$12,IF($C$16="","",EDATE($C$16,10-1)),"") -> 274 | C28: =IF(10<=$D$12,IF(10=1,$C$12,G27),"") -> 0 | D28: =IF(10<=$D$12,$F$12,"") -> 0 | E28: =IF(10<=$D$12,C28*($E$12/12),"") -> 0 | F28: =IF(10<=$D$12,D28-E28,"") -> 0 | G28: =IF(10<=$D$12,MAX(0,C28-F28),"") -> 0
A29: =IF(11<=$D$12,11,"") -> 11 | B29: =IF(11<=$D$12,IF($C$16="","",EDATE($C$16,11-1)),"") -> 305 | C29: =IF(11<=$D$12,IF(11=1,$C$12,G28),"") -> 0 | D29: =IF(11<=$D$12,$F$12,"") -> 0 | E29: =IF(11<=$D$12,C29*($E$12/12),"") -> 0 | F29: =IF(11<=$D$12,D29-E29,"") -> 0 | G29: =IF(11<=$D$12,MAX(0,C29-F29),"") -> 0
A30: =IF(12<=$D$12,12,"") -> 12 | B30: =IF(12<=$D$12,IF($C$16="","",EDATE($C$16,12-1)),"") -> 335 | C30: =IF(12<=$D$12,IF(12=1,$C$12,G29),"") -> 0 | D30: =IF(12<=$D$12,$F$12,"") -> 0 | E30: =IF(12<=$D$12,C30*($E$12/12),"") -> 0 | F30: =IF(12<=$D$12,D30-E30,"") -> 0 | G30: =IF(12<=$D$12,MAX(0,C30-F30),"") -> 0
A31: =IF(13<=$D$12,13,"") -> 13 | B31: =IF(13<=$D$12,IF($C$16="","",EDATE($C$16,13-1)),"") -> 366 | C31: =IF(13<=$D$12,IF(13=1,$C$12,G30),"") -> 0 | D31: =IF(13<=$D$12,$F$12,"") -> 0 | E31: =IF(13<=$D$12,C31*($E$12/12),"") -> 0 | F31: =IF(13<=$D$12,D31-E31,"") -> 0 | G31: =IF(13<=$D$12,MAX(0,C31-F31),"") -> 0
A32: =IF(14<=$D$12,14,"") -> 14 | B32: =IF(14<=$D$12,IF($C$16="","",EDATE($C$16,14-1)),"") -> 397 | C32: =IF(14<=$D$12,IF(14=1,$C$12,G31),"") -> 0 | D32: =IF(14<=$D$12,$F$12,"") -> 0 | E32: =IF(14<=$D$12,C32*($E$12/12),"") -> 0 | F32: =IF(14<=$D$12,D32-E32,"") -> 0 | G32: =IF(14<=$D$12,MAX(0,C32-F32),"") -> 0
A33: =IF(15<=$D$12,15,"") -> 15 | B33: =IF(15<=$D$12,IF($C$16="","",EDATE($C$16,15-1)),"") -> 425 | C33: =IF(15<=$D$12,IF(15=1,$C$12,G32),"") -> 0 | D33: =IF(15<=$D$12,$F$12,"") -> 0 | E33: =IF(15<=$D$12,C33*($E$12/12),"") -> 0 | F33: =IF(15<=$D$12,D33-E33,"") -> 0 | G33: =IF(15<=$D$12,MAX(0,C33-F33),"") -> 0
A34: =IF(16<=$D$12,16,"") -> 16 | B34: =IF(16<=$D$12,IF($C$16="","",EDATE($C$16,16-1)),"") -> 456 | C34: =IF(16<=$D$12,IF(16=1,$C$12,G33),"") -> 0 | D34: =IF(16<=$D$12,$F$12,"") -> 0 | E34: =IF(16<=$D$12,C34*($E$12/12),"") -> 0 | F34: =IF(16<=$D$12,D34-E34,"") -> 0 | G34: =IF(16<=$D$12,MAX(0,C34-F34),"") -> 0
A35: =IF(17<=$D$12,17,"") -> 17 | B35: =IF(17<=$D$12,IF($C$16="","",EDATE($C$16,17-1)),"") -> 486 | C35: =IF(17<=$D$12,IF(17=1,$C$12,G34),"") -> 0 | D35: =IF(17<=$D$12,$F$12,"") -> 0 | E35: =IF(17<=$D$12,C35*($E$12/12),"") -> 0 | F35: =IF(17<=$D$12,D35-E35,"") -> 0 | G35: =IF(17<=$D$12,MAX(0,C35-F35),"") -> 0
A36: =IF(18<=$D$12,18,"") -> 18 | B36: =IF(18<=$D$12,IF($C$16="","",EDATE($C$16,18-1)),"") -> 517 | C36: =IF(18<=$D$12,IF(18=1,$C$12,G35),"") -> 0 | D36: =IF(18<=$D$12,$F$12,"") -> 0 | E36: =IF(18<=$D$12,C36*($E$12/12),"") -> 0 | F36: =IF(18<=$D$12,D36-E36,"") -> 0 | G36: =IF(18<=$D$12,MAX(0,C36-F36),"") -> 0
A37: =IF(19<=$D$12,19,"") -> 19 | B37: =IF(19<=$D$12,IF($C$16="","",EDATE($C$16,19-1)),"") -> 547 | C37: =IF(19<=$D$12,IF(19=1,$C$12,G36),"") -> 0 | D37: =IF(19<=$D$12,$F$12,"") -> 0 | E37: =IF(19<=$D$12,C37*($E$12/12),"") -> 0 | F37: =IF(19<=$D$12,D37-E37,"") -> 0 | G37: =IF(19<=$D$12,MAX(0,C37-F37),"") -> 0
A38: =IF(20<=$D$12,20,"") -> 20 | B38: =IF(20<=$D$12,IF($C$16="","",EDATE($C$16,20-1)),"") -> 578 | C38: =IF(20<=$D$12,IF(20=1,$C$12,G37),"") -> 0 | D38: =IF(20<=$D$12,$F$12,"") -> 0 | E38: =IF(20<=$D$12,C38*($E$12/12),"") -> 0 | F38: =IF(20<=$D$12,D38-E38,"") -> 0 | G38: =IF(20<=$D$12,MAX(0,C38-F38),"") -> 0
A39: =IF(21<=$D$12,21,"") -> 21 | B39: =IF(21<=$D$12,IF($C$16="","",EDATE($C$16,21-1)),"") -> 609 | C39: =IF(21<=$D$12,IF(21=1,$C$12,G38),"") -> 0 | D39: =IF(21<=$D$12,$F$12,"") -> 0 | E39: =IF(21<=$D$12,C39*($E$12/12),"") -> 0 | F39: =IF(21<=$D$12,D39-E39,"") -> 0 | G39: =IF(21<=$D$12,MAX(0,C39-F39),"") -> 0
A40: =IF(22<=$D$12,22,"") -> 22 | B40: =IF(22<=$D$12,IF($C$16="","",EDATE($C$16,22-1)),"") -> 639 | C40: =IF(22<=$D$12,IF(22=1,$C$12,G39),"") -> 0 | D40: =IF(22<=$D$12,$F$12,"") -> 0 | E40: =IF(22<=$D$12,C40*($E$12/12),"") -> 0 | F40: =IF(22<=$D$12,D40-E40,"") -> 0 | G40: =IF(22<=$D$12,MAX(0,C40-F40),"") -> 0
A41: =IF(23<=$D$12,23,"") -> 23 | B41: =IF(23<=$D$12,IF($C$16="","",EDATE($C$16,23-1)),"") -> 670 | C41: =IF(23<=$D$12,IF(23=1,$C$12,G40),"") -> 0 | D41: =IF(23<=$D$12,$F$12,"") -> 0 | E41: =IF(23<=$D$12,C41*($E$12/12),"") -> 0 | F41: =IF(23<=$D$12,D41-E41,"") -> 0 | G41: =IF(23<=$D$12,MAX(0,C41-F41),"") -> 0
A42: =IF(24<=$D$12,24,"") -> 24 | B42: =IF(24<=$D$12,IF($C$16="","",EDATE($C$16,24-1)),"") -> 700 | C42: =IF(24<=$D$12,IF(24=1,$C$12,G41),"") -> 0 | D42: =IF(24<=$D$12,$F$12,"") -> 0 | E42: =IF(24<=$D$12,C42*($E$12/12),"") -> 0 | F42: =IF(24<=$D$12,D42-E42,"") -> 0 | G42: =IF(24<=$D$12,MAX(0,C42-F42),"") -> 0
A43: =IF(25<=$D$12,25,"") -> 25 | B43: =IF(25<=$D$12,IF($C$16="","",EDATE($C$16,25-1)),"") -> 731 | C43: =IF(25<=$D$12,IF(25=1,$C$12,G42),"") -> 0 | D43: =IF(25<=$D$12,$F$12,"") -> 0 | E43: =IF(25<=$D$12,C43*($E$12/12),"") -> 0 | F43: =IF(25<=$D$12,D43-E43,"") -> 0 | G43: =IF(25<=$D$12,MAX(0,C43-F43),"") -> 0
A44: =IF(26<=$D$12,26,"") -> 26 | B44: =IF(26<=$D$12,IF($C$16="","",EDATE($C$16,26-1)),"") -> 762 | C44: =IF(26<=$D$12,IF(26=1,$C$12,G43),"") -> 0 | D44: =IF(26<=$D$12,$F$12,"") -> 0 | E44: =IF(26<=$D$12,C44*($E$12/12),"") -> 0 | F44: =IF(26<=$D$12,D44-E44,"") -> 0 | G44: =IF(26<=$D$12,MAX(0,C44-F44),"") -> 0
A45: =IF(27<=$D$12,27,"") -> 27 | B45: =IF(27<=$D$12,IF($C$16="","",EDATE($C$16,27-1)),"") -> 790 | C45: =IF(27<=$D$12,IF(27=1,$C$12,G44),"") -> 0 | D45: =IF(27<=$D$12,$F$12,"") -> 0 | E45: =IF(27<=$D$12,C45*($E$12/12),"") -> 0 | F45: =IF(27<=$D$12,D45-E45,"") -> 0 | G45: =IF(27<=$D$12,MAX(0,C45-F45),"") -> 0
A46: =IF(28<=$D$12,28,"") -> 28 | B46: =IF(28<=$D$12,IF($C$16="","",EDATE($C$16,28-1)),"") -> 821 | C46: =IF(28<=$D$12,IF(28=1,$C$12,G45),"") -> 0 | D46: =IF(28<=$D$12,$F$12,"") -> 0 | E46: =IF(28<=$D$12,C46*($E$12/12),"") -> 0 | F46: =IF(28<=$D$12,D46-E46,"") -> 0 | G46: =IF(28<=$D$12,MAX(0,C46-F46),"") -> 0
A47: =IF(29<=$D$12,29,"") -> 29 | B47: =IF(29<=$D$12,IF($C$16="","",EDATE($C$16,29-1)),"") -> 851 | C47: =IF(29<=$D$12,IF(29=1,$C$12,G46),"") -> 0 | D47: =IF(29<=$D$12,$F$12,"") -> 0 | E47: =IF(29<=$D$12,C47*($E$12/12),"") -> 0 | F47: =IF(29<=$D$12,D47-E47,"") -> 0 | G47: =IF(29<=$D$12,MAX(0,C47-F47),"") -> 0
A48: =IF(30<=$D$12,30,"") -> 30 | B48: =IF(30<=$D$12,IF($C$16="","",EDATE($C$16,30-1)),"") -> 882 | C48: =IF(30<=$D$12,IF(30=1,$C$12,G47),"") -> 0 | D48: =IF(30<=$D$12,$F$12,"") -> 0 | E48: =IF(30<=$D$12,C48*($E$12/12),"") -> 0 | F48: =IF(30<=$D$12,D48-E48,"") -> 0 | G48: =IF(30<=$D$12,MAX(0,C48-F48),"") -> 0
A49: =IF(31<=$D$12,31,"") -> 31 | B49: =IF(31<=$D$12,IF($C$16="","",EDATE($C$16,31-1)),"") -> 912 | C49: =IF(31<=$D$12,IF(31=1,$C$12,G48),"") -> 0 | D49: =IF(31<=$D$12,$F$12,"") -> 0 | E49: =IF(31<=$D$12,C49*($E$12/12),"") -> 0 | F49: =IF(31<=$D$12,D49-E49,"") -> 0 | G49: =IF(31<=$D$12,MAX(0,C49-F49),"") -> 0
A50: =IF(32<=$D$12,32,"") -> 32 | B50: =IF(32<=$D$12,IF($C$16="","",EDATE($C$16,32-1)),"") -> 943 | C50: =IF(32<=$D$12,IF(32=1,$C$12,G49),"") -> 0 | D50: =IF(32<=$D$12,$F$12,"") -> 0 | E50: =IF(32<=$D$12,C50*($E$12/12),"") -> 0 | F50: =IF(32<=$D$12,D50-E50,"") -> 0 | G50: =IF(32<=$D$12,MAX(0,C50-F50),"") -> 0
A51: =IF(33<=$D$12,33,"") -> 33 | B51: =IF(33<=$D$12,IF($C$16="","",EDATE($C$16,33-1)),"") -> 974 | C51: =IF(33<=$D$12,IF(33=1,$C$12,G50),"") -> 0 | D51: =IF(33<=$D$12,$F$12,"") -> 0 | E51: =IF(33<=$D$12,C51*($E$12/12),"") -> 0 | F51: =IF(33<=$D$12,D51-E51,"") -> 0 | G51: =IF(33<=$D$12,MAX(0,C51-F51),"") -> 0
A52: =IF(34<=$D$12,34,"") -> 34 | B52: =IF(34<=$D$12,IF($C$16="","",EDATE($C$16,34-1)),"") -> 1004 | C52: =IF(34<=$D$12,IF(34=1,$C$12,G51),"") -> 0 | D52: =IF(34<=$D$12,$F$12,"") -> 0 | E52: =IF(34<=$D$12,C52*($E$12/12),"") -> 0 | F52: =IF(34<=$D$12,D52-E52,"") -> 0 | G52: =IF(34<=$D$12,MAX(0,C52-F52),"") -> 0
A53: =IF(35<=$D$12,35,"") -> 35 | B53: =IF(35<=$D$12,IF($C$16="","",EDATE($C$16,35-1)),"") -> 1035 | C53: =IF(35<=$D$12,IF(35=1,$C$12,G52),"") -> 0 | D53: =IF(35<=$D$12,$F$12,"") -> 0 | E53: =IF(35<=$D$12,C53*($E$12/12),"") -> 0 | F53: =IF(35<=$D$12,D53-E53,"") -> 0 | G53: =IF(35<=$D$12,MAX(0,C53-F53),"") -> 0
A54: =IF(36<=$D$12,36,"") -> 36 | B54: =IF(36<=$D$12,IF($C$16="","",EDATE($C$16,36-1)),"") -> 1065 | C54: =IF(36<=$D$12,IF(36=1,$C$12,G53),"") -> 0 | D54: =IF(36<=$D$12,$F$12,"") -> 0 | E54: =IF(36<=$D$12,C54*($E$12/12),"") -> 0 | F54: =IF(36<=$D$12,D54-E54,"") -> 0 | G54: =IF(36<=$D$12,MAX(0,C54-F54),"") -> 0
A55: =IF(37<=$D$12,37,"") -> 37 | B55: =IF(37<=$D$12,IF($C$16="","",EDATE($C$16,37-1)),"") -> 1096 | C55: =IF(37<=$D$12,IF(37=1,$C$12,G54),"") -> 0 | D55: =IF(37<=$D$12,$F$12,"") -> 0 | E55: =IF(37<=$D$12,C55*($E$12/12),"") -> 0 | F55: =IF(37<=$D$12,D55-E55,"") -> 0 | G55: =IF(37<=$D$12,MAX(0,C55-F55),"") -> 0
A56: =IF(38<=$D$12,38,"") -> 38 | B56: =IF(38<=$D$12,IF($C$16="","",EDATE($C$16,38-1)),"") -> 1127 | C56: =IF(38<=$D$12,IF(38=1,$C$12,G55),"") -> 0 | D56: =IF(38<=$D$12,$F$12,"") -> 0 | E56: =IF(38<=$D$12,C56*($E$12/12),"") -> 0 | F56: =IF(38<=$D$12,D56-E56,"") -> 0 | G56: =IF(38<=$D$12,MAX(0,C56-F56),"") -> 0
A57: =IF(39<=$D$12,39,"") -> 39 | B57: =IF(39<=$D$12,IF($C$16="","",EDATE($C$16,39-1)),"") -> 1155 | C57: =IF(39<=$D$12,IF(39=1,$C$12,G56),"") -> 0 | D57: =IF(39<=$D$12,$F$12,"") -> 0 | E57: =IF(39<=$D$12,C57*($E$12/12),"") -> 0 | F57: =IF(39<=$D$12,D57-E57,"") -> 0 | G57: =IF(39<=$D$12,MAX(0,C57-F57),"") -> 0
A58: =IF(40<=$D$12,40,"") -> 40 | B58: =IF(40<=$D$12,IF($C$16="","",EDATE($C$16,40-1)),"") -> 1186 | C58: =IF(40<=$D$12,IF(40=1,$C$12,G57),"") -> 0 | D58: =IF(40<=$D$12,$F$12,"") -> 0 | E58: =IF(40<=$D$12,C58*($E$12/12),"") -> 0 | F58: =IF(40<=$D$12,D58-E58,"") -> 0 | G58: =IF(40<=$D$12,MAX(0,C58-F58),"") -> 0
A59: =IF(41<=$D$12,41,"") -> 41 | B59: =IF(41<=$D$12,IF($C$16="","",EDATE($C$16,41-1)),"") -> 1216 | C59: =IF(41<=$D$12,IF(41=1,$C$12,G58),"") -> 0 | D59: =IF(41<=$D$12,$F$12,"") -> 0 | E59: =IF(41<=$D$12,C59*($E$12/12),"") -> 0 | F59: =IF(41<=$D$12,D59-E59,"") -> 0 | G59: =IF(41<=$D$12,MAX(0,C59-F59),"") -> 0
A60: =IF(42<=$D$12,42,"") -> 42 | B60: =IF(42<=$D$12,IF($C$16="","",EDATE($C$16,42-1)),"") -> 1247 | C60: =IF(42<=$D$12,IF(42=1,$C$12,G59),"") -> 0 | D60: =IF(42<=$D$12,$F$12,"") -> 0 | E60: =IF(42<=$D$12,C60*($E$12/12),"") -> 0 | F60: =IF(42<=$D$12,D60-E60,"") -> 0 | G60: =IF(42<=$D$12,MAX(0,C60-F60),"") -> 0
A61: =IF(43<=$D$12,43,"") -> 43 | B61: =IF(43<=$D$12,IF($C$16="","",EDATE($C$16,43-1)),"") -> 1277 | C61: =IF(43<=$D$12,IF(43=1,$C$12,G60),"") -> 0 | D61: =IF(43<=$D$12,$F$12,"") -> 0 | E61: =IF(43<=$D$12,C61*($E$12/12),"") -> 0 | F61: =IF(43<=$D$12,D61-E61,"") -> 0 | G61: =IF(43<=$D$12,MAX(0,C61-F61),"") -> 0
A62: =IF(44<=$D$12,44,"") -> 44 | B62: =IF(44<=$D$12,IF($C$16="","",EDATE($C$16,44-1)),"") -> 1308 | C62: =IF(44<=$D$12,IF(44=1,$C$12,G61),"") -> 0 | D62: =IF(44<=$D$12,$F$12,"") -> 0 | E62: =IF(44<=$D$12,C62*($E$12/12),"") -> 0 | F62: =IF(44<=$D$12,D62-E62,"") -> 0 | G62: =IF(44<=$D$12,MAX(0,C62-F62),"") -> 0
A63: =IF(45<=$D$12,45,"") -> 45 | B63: =IF(45<=$D$12,IF($C$16="","",EDATE($C$16,45-1)),"") -> 1339 | C63: =IF(45<=$D$12,IF(45=1,$C$12,G62),"") -> 0 | D63: =IF(45<=$D$12,$F$12,"") -> 0 | E63: =IF(45<=$D$12,C63*($E$12/12),"") -> 0 | F63: =IF(45<=$D$12,D63-E63,"") -> 0 | G63: =IF(45<=$D$12,MAX(0,C63-F63),"") -> 0
A64: =IF(46<=$D$12,46,"") -> 46 | B64: =IF(46<=$D$12,IF($C$16="","",EDATE($C$16,46-1)),"") -> 1369 | C64: =IF(46<=$D$12,IF(46=1,$C$12,G63),"") -> 0 | D64: =IF(46<=$D$12,$F$12,"") -> 0 | E64: =IF(46<=$D$12,C64*($E$12/12),"") -> 0 | F64: =IF(46<=$D$12,D64-E64,"") -> 0 | G64: =IF(46<=$D$12,MAX(0,C64-F64),"") -> 0
A65: =IF(47<=$D$12,47,"") -> 47 | B65: =IF(47<=$D$12,IF($C$16="","",EDATE($C$16,47-1)),"") -> 1400 | C65: =IF(47<=$D$12,IF(47=1,$C$12,G64),"") -> 0 | D65: =IF(47<=$D$12,$F$12,"") -> 0 | E65: =IF(47<=$D$12,C65*($E$12/12),"") -> 0 | F65: =IF(47<=$D$12,D65-E65,"") -> 0 | G65: =IF(47<=$D$12,MAX(0,C65-F65),"") -> 0
A66: =IF(48<=$D$12,48,"") -> 48 | B66: =IF(48<=$D$12,IF($C$16="","",EDATE($C$16,48-1)),"") -> 1430 | C66: =IF(48<=$D$12,IF(48=1,$C$12,G65),"") -> 0 | D66: =IF(48<=$D$12,$F$12,"") -> 0 | E66: =IF(48<=$D$12,C66*($E$12/12),"") -> 0 | F66: =IF(48<=$D$12,D66-E66,"") -> 0 | G66: =IF(48<=$D$12,MAX(0,C66-F66),"") -> 0
A67: =IF(49<=$D$12,49,"") -> 49 | B67: =IF(49<=$D$12,IF($C$16="","",EDATE($C$16,49-1)),"") -> 1461 | C67: =IF(49<=$D$12,IF(49=1,$C$12,G66),"") -> 0 | D67: =IF(49<=$D$12,$F$12,"") -> 0 | E67: =IF(49<=$D$12,C67*($E$12/12),"") -> 0 | F67: =IF(49<=$D$12,D67-E67,"") -> 0 | G67: =IF(49<=$D$12,MAX(0,C67-F67),"") -> 0
A68: =IF(50<=$D$12,50,"") -> 50 | B68: =IF(50<=$D$12,IF($C$16="","",EDATE($C$16,50-1)),"") -> 1492 | C68: =IF(50<=$D$12,IF(50=1,$C$12,G67),"") -> 0 | D68: =IF(50<=$D$12,$F$12,"") -> 0 | E68: =IF(50<=$D$12,C68*($E$12/12),"") -> 0 | F68: =IF(50<=$D$12,D68-E68,"") -> 0 | G68: =IF(50<=$D$12,MAX(0,C68-F68),"") -> 0
A69: =IF(51<=$D$12,51,"") -> 51 | B69: =IF(51<=$D$12,IF($C$16="","",EDATE($C$16,51-1)),"") -> 1521 | C69: =IF(51<=$D$12,IF(51=1,$C$12,G68),"") -> 0 | D69: =IF(51<=$D$12,$F$12,"") -> 0 | E69: =IF(51<=$D$12,C69*($E$12/12),"") -> 0 | F69: =IF(51<=$D$12,D69-E69,"") -> 0 | G69: =IF(51<=$D$12,MAX(0,C69-F69),"") -> 0
A70: =IF(52<=$D$12,52,"") -> 52 | B70: =IF(52<=$D$12,IF($C$16="","",EDATE($C$16,52-1)),"") -> 1552 | C70: =IF(52<=$D$12,IF(52=1,$C$12,G69),"") -> 0 | D70: =IF(52<=$D$12,$F$12,"") -> 0 | E70: =IF(52<=$D$12,C70*($E$12/12),"") -> 0 | F70: =IF(52<=$D$12,D70-E70,"") -> 0 | G70: =IF(52<=$D$12,MAX(0,C70-F70),"") -> 0
A71: =IF(53<=$D$12,53,"") -> 53 | B71: =IF(53<=$D$12,IF($C$16="","",EDATE($C$16,53-1)),"") -> 1582 | C71: =IF(53<=$D$12,IF(53=1,$C$12,G70),"") -> 0 | D71: =IF(53<=$D$12,$F$12,"") -> 0 | E71: =IF(53<=$D$12,C71*($E$12/12),"") -> 0 | F71: =IF(53<=$D$12,D71-E71,"") -> 0 | G71: =IF(53<=$D$12,MAX(0,C71-F71),"") -> 0
A72: =IF(54<=$D$12,54,"") -> 54 | B72: =IF(54<=$D$12,IF($C$16="","",EDATE($C$16,54-1)),"") -> 1613 | C72: =IF(54<=$D$12,IF(54=1,$C$12,G71),"") -> 0 | D72: =IF(54<=$D$12,$F$12,"") -> 0 | E72: =IF(54<=$D$12,C72*($E$12/12),"") -> 0 | F72: =IF(54<=$D$12,D72-E72,"") -> 0 | G72: =IF(54<=$D$12,MAX(0,C72-F72),"") -> 0
A73: =IF(55<=$D$12,55,"") -> 55 | B73: =IF(55<=$D$12,IF($C$16="","",EDATE($C$16,55-1)),"") -> 1643 | C73: =IF(55<=$D$12,IF(55=1,$C$12,G72),"") -> 0 | D73: =IF(55<=$D$12,$F$12,"") -> 0 | E73: =IF(55<=$D$12,C73*($E$12/12),"") -> 0 | F73: =IF(55<=$D$12,D73-E73,"") -> 0 | G73: =IF(55<=$D$12,MAX(0,C73-F73),"") -> 0
A74: =IF(56<=$D$12,56,"") -> 56 | B74: =IF(56<=$D$12,IF($C$16="","",EDATE($C$16,56-1)),"") -> 1674 | C74: =IF(56<=$D$12,IF(56=1,$C$12,G73),"") -> 0 | D74: =IF(56<=$D$12,$F$12,"") -> 0 | E74: =IF(56<=$D$12,C74*($E$12/12),"") -> 0 | F74: =IF(56<=$D$12,D74-E74,"") -> 0 | G74: =IF(56<=$D$12,MAX(0,C74-F74),"") -> 0
A75: =IF(57<=$D$12,57,"") -> 57 | B75: =IF(57<=$D$12,IF($C$16="","",EDATE($C$16,57-1)),"") -> 1705 | C75: =IF(57<=$D$12,IF(57=1,$C$12,G74),"") -> 0 | D75: =IF(57<=$D$12,$F$12,"") -> 0 | E75: =IF(57<=$D$12,C75*($E$12/12),"") -> 0 | F75: =IF(57<=$D$12,D75-E75,"") -> 0 | G75: =IF(57<=$D$12,MAX(0,C75-F75),"") -> 0
A76: =IF(58<=$D$12,58,"") -> 58 | B76: =IF(58<=$D$12,IF($C$16="","",EDATE($C$16,58-1)),"") -> 1735 | C76: =IF(58<=$D$12,IF(58=1,$C$12,G75),"") -> 0 | D76: =IF(58<=$D$12,$F$12,"") -> 0 | E76: =IF(58<=$D$12,C76*($E$12/12),"") -> 0 | F76: =IF(58<=$D$12,D76-E76,"") -> 0 | G76: =IF(58<=$D$12,MAX(0,C76-F76),"") -> 0
A77: =IF(59<=$D$12,59,"") -> 59 | B77: =IF(59<=$D$12,IF($C$16="","",EDATE($C$16,59-1)),"") -> 1766 | C77: =IF(59<=$D$12,IF(59=1,$C$12,G76),"") -> 0 | D77: =IF(59<=$D$12,$F$12,"") -> 0 | E77: =IF(59<=$D$12,C77*($E$12/12),"") -> 0 | F77: =IF(59<=$D$12,D77-E77,"") -> 0 | G77: =IF(59<=$D$12,MAX(0,C77-F77),"") -> 0
A78: =IF(60<=$D$12,60,"") -> 60 | B78: =IF(60<=$D$12,IF($C$16="","",EDATE($C$16,60-1)),"") -> 1796 | C78: =IF(60<=$D$12,IF(60=1,$C$12,G77),"") -> 0 | D78: =IF(60<=$D$12,$F$12,"") -> 0 | E78: =IF(60<=$D$12,C78*($E$12/12),"") -> 0 | F78: =IF(60<=$D$12,D78-E78,"") -> 0 | G78: =IF(60<=$D$12,MAX(0,C78-F78),"") -> 0
A79: =IF(61<=$D$12,61,"") -> 61 | B79: =IF(61<=$D$12,IF($C$16="","",EDATE($C$16,61-1)),"") -> 1827 | C79: =IF(61<=$D$12,IF(61=1,$C$12,G78),"") -> 0 | D79: =IF(61<=$D$12,$F$12,"") -> 0 | E79: =IF(61<=$D$12,C79*($E$12/12),"") -> 0 | F79: =IF(61<=$D$12,D79-E79,"") -> 0 | G79: =IF(61<=$D$12,MAX(0,C79-F79),"") -> 0
A80: =IF(62<=$D$12,62,"") -> 62 | B80: =IF(62<=$D$12,IF($C$16="","",EDATE($C$16,62-1)),"") -> 1858 | C80: =IF(62<=$D$12,IF(62=1,$C$12,G79),"") -> 0 | D80: =IF(62<=$D$12,$F$12,"") -> 0 | E80: =IF(62<=$D$12,C80*($E$12/12),"") -> 0 | F80: =IF(62<=$D$12,D80-E80,"") -> 0 | G80: =IF(62<=$D$12,MAX(0,C80-F80),"") -> 0
A81: =IF(63<=$D$12,63,"") -> 63 | B81: =IF(63<=$D$12,IF($C$16="","",EDATE($C$16,63-1)),"") -> 1886 | C81: =IF(63<=$D$12,IF(63=1,$C$12,G80),"") -> 0 | D81: =IF(63<=$D$12,$F$12,"") -> 0 | E81: =IF(63<=$D$12,C81*($E$12/12),"") -> 0 | F81: =IF(63<=$D$12,D81-E81,"") -> 0 | G81: =IF(63<=$D$12,MAX(0,C81-F81),"") -> 0
A82: =IF(64<=$D$12,64,"") -> 64 | B82: =IF(64<=$D$12,IF($C$16="","",EDATE($C$16,64-1)),"") -> 1917 | C82: =IF(64<=$D$12,IF(64=1,$C$12,G81),"") -> 0 | D82: =IF(64<=$D$12,$F$12,"") -> 0 | E82: =IF(64<=$D$12,C82*($E$12/12),"") -> 0 | F82: =IF(64<=$D$12,D82-E82,"") -> 0 | G82: =IF(64<=$D$12,MAX(0,C82-F82),"") -> 0
A83: =IF(65<=$D$12,65,"") -> 65 | B83: =IF(65<=$D$12,IF($C$16="","",EDATE($C$16,65-1)),"") -> 1947 | C83: =IF(65<=$D$12,IF(65=1,$C$12,G82),"") -> 0 | D83: =IF(65<=$D$12,$F$12,"") -> 0 | E83: =IF(65<=$D$12,C83*($E$12/12),"") -> 0 | F83: =IF(65<=$D$12,D83-E83,"") -> 0 | G83: =IF(65<=$D$12,MAX(0,C83-F83),"") -> 0
A84: =IF(66<=$D$12,66,"") -> 66 | B84: =IF(66<=$D$12,IF($C$16="","",EDATE($C$16,66-1)),"") -> 1978 | C84: =IF(66<=$D$12,IF(66=1,$C$12,G83),"") -> 0 | D84: =IF(66<=$D$12,$F$12,"") -> 0 | E84: =IF(66<=$D$12,C84*($E$12/12),"") -> 0 | F84: =IF(66<=$D$12,D84-E84,"") -> 0 | G84: =IF(66<=$D$12,MAX(0,C84-F84),"") -> 0
A85: =IF(67<=$D$12,67,"") -> 67 | B85: =IF(67<=$D$12,IF($C$16="","",EDATE($C$16,67-1)),"") -> 2008 | C85: =IF(67<=$D$12,IF(67=1,$C$12,G84),"") -> 0 | D85: =IF(67<=$D$12,$F$12,"") -> 0 | E85: =IF(67<=$D$12,C85*($E$12/12),"") -> 0 | F85: =IF(67<=$D$12,D85-E85,"") -> 0 | G85: =IF(67<=$D$12,MAX(0,C85-F85),"") -> 0
A86: =IF(68<=$D$12,68,"") -> 68 | B86: =IF(68<=$D$12,IF($C$16="","",EDATE($C$16,68-1)),"") -> 2039 | C86: =IF(68<=$D$12,IF(68=1,$C$12,G85),"") -> 0 | D86: =IF(68<=$D$12,$F$12,"") -> 0 | E86: =IF(68<=$D$12,C86*($E$12/12),"") -> 0 | F86: =IF(68<=$D$12,D86-E86,"") -> 0 | G86: =IF(68<=$D$12,MAX(0,C86-F86),"") -> 0
A87: =IF(69<=$D$12,69,"") -> 69 | B87: =IF(69<=$D$12,IF($C$16="","",EDATE($C$16,69-1)),"") -> 2070 | C87: =IF(69<=$D$12,IF(69=1,$C$12,G86),"") -> 0 | D87: =IF(69<=$D$12,$F$12,"") -> 0 | E87: =IF(69<=$D$12,C87*($E$12/12),"") -> 0 | F87: =IF(69<=$D$12,D87-E87,"") -> 0 | G87: =IF(69<=$D$12,MAX(0,C87-F87),"") -> 0
A88: =IF(70<=$D$12,70,"") -> 70 | B88: =IF(70<=$D$12,IF($C$16="","",EDATE($C$16,70-1)),"") -> 2100 | C88: =IF(70<=$D$12,IF(70=1,$C$12,G87),"") -> 0 | D88: =IF(70<=$D$12,$F$12,"") -> 0 | E88: =IF(70<=$D$12,C88*($E$12/12),"") -> 0 | F88: =IF(70<=$D$12,D88-E88,"") -> 0 | G88: =IF(70<=$D$12,MAX(0,C88-F88),"") -> 0
A89: =IF(71<=$D$12,71,"") -> 71 | B89: =IF(71<=$D$12,IF($C$16="","",EDATE($C$16,71-1)),"") -> 2131 | C89: =IF(71<=$D$12,IF(71=1,$C$12,G88),"") -> 0 | D89: =IF(71<=$D$12,$F$12,"") -> 0 | E89: =IF(71<=$D$12,C89*($E$12/12),"") -> 0 | F89: =IF(71<=$D$12,D89-E89,"") -> 0 | G89: =IF(71<=$D$12,MAX(0,C89-F89),"") -> 0
A90: =IF(72<=$D$12,72,"") -> 72 | B90: =IF(72<=$D$12,IF($C$16="","",EDATE($C$16,72-1)),"") -> 2161 | C90: =IF(72<=$D$12,IF(72=1,$C$12,G89),"") -> 0 | D90: =IF(72<=$D$12,$F$12,"") -> 0 | E90: =IF(72<=$D$12,C90*($E$12/12),"") -> 0 | F90: =IF(72<=$D$12,D90-E90,"") -> 0 | G90: =IF(72<=$D$12,MAX(0,C90-F90),"") -> 0
A91: =IF(73<=$D$12,73,"") -> 73 | B91: =IF(73<=$D$12,IF($C$16="","",EDATE($C$16,73-1)),"") -> 2192 | C91: =IF(73<=$D$12,IF(73=1,$C$12,G90),"") -> 0 | D91: =IF(73<=$D$12,$F$12,"") -> 0 | E91: =IF(73<=$D$12,C91*($E$12/12),"") -> 0 | F91: =IF(73<=$D$12,D91-E91,"") -> 0 | G91: =IF(73<=$D$12,MAX(0,C91-F91),"") -> 0
A92: =IF(74<=$D$12,74,"") -> 74 | B92: =IF(74<=$D$12,IF($C$16="","",EDATE($C$16,74-1)),"") -> 2223 | C92: =IF(74<=$D$12,IF(74=1,$C$12,G91),"") -> 0 | D92: =IF(74<=$D$12,$F$12,"") -> 0 | E92: =IF(74<=$D$12,C92*($E$12/12),"") -> 0 | F92: =IF(74<=$D$12,D92-E92,"") -> 0 | G92: =IF(74<=$D$12,MAX(0,C92-F92),"") -> 0
A93: =IF(75<=$D$12,75,"") -> 75 | B93: =IF(75<=$D$12,IF($C$16="","",EDATE($C$16,75-1)),"") -> 2251 | C93: =IF(75<=$D$12,IF(75=1,$C$12,G92),"") -> 0 | D93: =IF(75<=$D$12,$F$12,"") -> 0 | E93: =IF(75<=$D$12,C93*($E$12/12),"") -> 0 | F93: =IF(75<=$D$12,D93-E93,"") -> 0 | G93: =IF(75<=$D$12,MAX(0,C93-F93),"") -> 0
A94: =IF(76<=$D$12,76,"") -> 76 | B94: =IF(76<=$D$12,IF($C$16="","",EDATE($C$16,76-1)),"") -> 2282 | C94: =IF(76<=$D$12,IF(76=1,$C$12,G93),"") -> 0 | D94: =IF(76<=$D$12,$F$12,"") -> 0 | E94: =IF(76<=$D$12,C94*($E$12/12),"") -> 0 | F94: =IF(76<=$D$12,D94-E94,"") -> 0 | G94: =IF(76<=$D$12,MAX(0,C94-F94),"") -> 0
A95: =IF(77<=$D$12,77,"") -> 77 | B95: =IF(77<=$D$12,IF($C$16="","",EDATE($C$16,77-1)),"") -> 2312 | C95: =IF(77<=$D$12,IF(77=1,$C$12,G94),"") -> 0 | D95: =IF(77<=$D$12,$F$12,"") -> 0 | E95: =IF(77<=$D$12,C95*($E$12/12),"") -> 0 | F95: =IF(77<=$D$12,D95-E95,"") -> 0 | G95: =IF(77<=$D$12,MAX(0,C95-F95),"") -> 0
A96: =IF(78<=$D$12,78,"") -> 78 | B96: =IF(78<=$D$12,IF($C$16="","",EDATE($C$16,78-1)),"") -> 2343 | C96: =IF(78<=$D$12,IF(78=1,$C$12,G95),"") -> 0 | D96: =IF(78<=$D$12,$F$12,"") -> 0 | E96: =IF(78<=$D$12,C96*($E$12/12),"") -> 0 | F96: =IF(78<=$D$12,D96-E96,"") -> 0 | G96: =IF(78<=$D$12,MAX(0,C96-F96),"") -> 0
A97: =IF(79<=$D$12,79,"") -> 79 | B97: =IF(79<=$D$12,IF($C$16="","",EDATE($C$16,79-1)),"") -> 2373 | C97: =IF(79<=$D$12,IF(79=1,$C$12,G96),"") -> 0 | D97: =IF(79<=$D$12,$F$12,"") -> 0 | E97: =IF(79<=$D$12,C97*($E$12/12),"") -> 0 | F97: =IF(79<=$D$12,D97-E97,"") -> 0 | G97: =IF(79<=$D$12,MAX(0,C97-F97),"") -> 0
A98: =IF(80<=$D$12,80,"") -> 80 | B98: =IF(80<=$D$12,IF($C$16="","",EDATE($C$16,80-1)),"") -> 2404 | C98: =IF(80<=$D$12,IF(80=1,$C$12,G97),"") -> 0 | D98: =IF(80<=$D$12,$F$12,"") -> 0 | E98: =IF(80<=$D$12,C98*($E$12/12),"") -> 0 | F98: =IF(80<=$D$12,D98-E98,"") -> 0 | G98: =IF(80<=$D$12,MAX(0,C98-F98),"") -> 0
A99: =IF(81<=$D$12,81,"") -> 81 | B99: =IF(81<=$D$12,IF($C$16="","",EDATE($C$16,81-1)),"") -> 2435 | C99: =IF(81<=$D$12,IF(81=1,$C$12,G98),"") -> 0 | D99: =IF(81<=$D$12,$F$12,"") -> 0 | E99: =IF(81<=$D$12,C99*($E$12/12),"") -> 0 | F99: =IF(81<=$D$12,D99-E99,"") -> 0 | G99: =IF(81<=$D$12,MAX(0,C99-F99),"") -> 0
A100: =IF(82<=$D$12,82,"") -> 82 | B100: =IF(82<=$D$12,IF($C$16="","",EDATE($C$16,82-1)),"") -> 2465 | C100: =IF(82<=$D$12,IF(82=1,$C$12,G99),"") -> 0 | D100: =IF(82<=$D$12,$F$12,"") -> 0 | E100: =IF(82<=$D$12,C100*($E$12/12),"") -> 0 | F100: =IF(82<=$D$12,D100-E100,"") -> 0 | G100: =IF(82<=$D$12,MAX(0,C100-F100),"") -> 0
A101: =IF(83<=$D$12,83,"") -> 83 | B101: =IF(83<=$D$12,IF($C$16="","",EDATE($C$16,83-1)),"") -> 2496 | C101: =IF(83<=$D$12,IF(83=1,$C$12,G100),"") -> 0 | D101: =IF(83<=$D$12,$F$12,"") -> 0 | E101: =IF(83<=$D$12,C101*($E$12/12),"") -> 0 | F101: =IF(83<=$D$12,D101-E101,"") -> 0 | G101: =IF(83<=$D$12,MAX(0,C101-F101),"") -> 0
A102: =IF(84<=$D$12,84,"") -> 84 | B102: =IF(84<=$D$12,IF($C$16="","",EDATE($C$16,84-1)),"") -> 2526 | C102: =IF(84<=$D$12,IF(84=1,$C$12,G101),"") -> 0 | D102: =IF(84<=$D$12,$F$12,"") -> 0 | E102: =IF(84<=$D$12,C102*($E$12/12),"") -> 0 | F102: =IF(84<=$D$12,D102-E102,"") -> 0 | G102: =IF(84<=$D$12,MAX(0,C102-F102),"") -> 0
...
