Workbook

Sheet Solicitud
A1: COOPERATIVA MIXTA DE FARMACÉUTICOS DE HONDURAS (COMIFARH)
A3: SOLICITUD DE PRÉSTAMO FIDUCIARIO
A4: RESUMEN DEL CRÉDITO
A5: Monto solicitado (L) | B5: =B35 -> 0
A6: Plazo (meses) | B6: =B36 -> 0
A7: Tasa anual | B7: ='Análisis de Crédito'!B5 -> 0.18
A8: Cuota estimada | B8: =Amortización!F12 -> #DIV/0!
A9: Retención 5% | B9: =B35*'Análisis de Crédito'!B7 -> 0
A10: Gastos 3% | B10: =B35*'Análisis de Crédito'!B8 -> 0
A11: Desembolso neto | B11: =B35-B9-B10 -> 0
A13: I. DATOS GENERALES DEL SOLICITANTE
A14: Fecha de solicitud
A15: Número de asociado
A16: Nombre completo
A17: Tipo de identificación
A18: Número de identificación
A19: Fecha de nacimiento
A20: Estado civil
A21: Dirección completa
A22: Departamento
A23: Municipio
A24: Teléfono
... A80: CHECKLIST DE DOCUMENTOS (marque): ☐ Identidad ☐ Constancia de trabajo/Estados fin. ☐ RTN (si aplica) ☐ Aval o Seguro de deuda ☐ Otros

Sheet Listas
A1: tipo_id | B1: DNI | C1: RTN | D1: Pasaporte
A2: estado_civil | B2: Soltero(a) | C2: Casado(a) | D2: Unión libre | E2: Divorciado(a) | F2: Viudo(a)
A3: cond_laboral | B3: Empleado(a) público | C3: Empleado(a) privado | D3: Negocio propio | E3: Jubilado(a)
A4: plazo | B4: 6 | C4: 12 | D4: 18 | E4: 24 | F4: 36 | G4: 48 | H4: 60 | I4: 72
A5: forma_pago | B5: Deducción por planilla | C5: Pago en ventanilla | D5: Transferencia bancaria
A6: destino | B6: Consumo personal | C6: Educación | D6: Salud | E6: Consolidación de deudas | F6: Vivienda | G6: Otro
A7: parentesco | B7: Familiar | C7: Amistad
A8: recomendacion | B8: Aprobado | C8: Condicionado | D8: Rechazado
A9: si_no | B9: Sí | C9: No
A10: departamento | B10: Atlántida | C10: Choluteca | D10: Colón | E10: Comayagua | F10: Copán | G10: Cortés | H10: El Paraíso | I10: Francisco Morazán | J10: Gracias a Dios | K10: Intibucá | L10: Islas de la Bahía | M10: La Paz | N10: Lempira | O10: Ocotepeque | P10: Olancho | Q10: Santa Bárbara | R10: Valle | S10: Yoro
A11: aval_es_socio | B11: Socio | C11: No socio
A12: relacion_aval | B12: Familiar | C12: Amistad | D12: Compañero(a) de trabajo | E12: Otro

Sheet Análisis de Crédito
A1: ANÁLISIS DE CRÉDITO – PRÉSTAMO FIDUCICIARIO (COMIFARH)
A4: 1) PARÁMETROS
A5: Tasa anual fiduciario | B5: 0.18 | D5: Editable por analista/Junta Directiva
A6: Máx. relación deuda/ingreso neto | B6: 0.3 | D6: Editable
A7: Retención a aportaciones | B7: 0.05 | D7: Editable
A8: Gastos operativos | B8: 0.03 | D8: Editable
A9: Techo fiduciario (L) | B9: 300000 | D9: Editable
A10: Plazo máximo permitido (meses) | B10: 72 | D10: Editable
A12: 2) DATOS (desde Solicitud)
A13: Ingreso mensual neto (L) | B13: =Solicitud!B33 -> 0
A14: Total aportaciones (L) | B14: =Solicitud!B42 -> 0
A15: Monto solicitado (L) | B15: =Solicitud!B35 -> 0
A16: Plazo solicitado (meses) | B16: =Solicitud!B36 -> 0
A17: Aportación mensual vigente (L) | B17: =Solicitud!B45 -> 0
A19: 3) OBLIGACIONES (ingrese)
A20: Cuotas de préstamos vigentes (L)
A21: Gastos fijos estimados (L) | B21: 3000
A22: Total egresos (L) | B22: =SUM(B20:B21) -> 3000
A24: 4) CÁLCULO
A25: Monto máximo por aportaciones (5x) (L) | B25: =5*B14 -> 0
A26: Monto máximo permitido (L) | B26: =MIN(B25,$B$9) -> 0
A27: Tasa mensual | B27: =$B$5/12 -> 0.015
A28: Retención 5% (L) | B28: =B15*$B$7 -> 0
A29: Gastos operativos 3% (L) | B29: =B15*$B$8 -> 0
A30: Desembolso neto estimado (L) | B30: =B15-B28-B29 -> 0
A31: Cuota mensual estimada (L) | B31: =-PMT(B27,B16,B15) -> #NUM!
A32: Cuota total (incluye aportación) (L) | B32: =B31+B17 -> #NUM!
A33: Relación deuda/ingreso neto (%) | B33: =(B32+B22)/B13 -> #NUM!
A34: Cumple relación ≤ límite | B34: =IF(B33<=$B$6,"SÍ","NO") -> #NUM!
A35: Cumple monto ≤ máximo | B35: =IF(B16<=B26,"SÍ","NO") -> SÍ
A36: Plazo dentro del máximo | B36: =IF(B16<=$B$10,"SÍ","NO") -> SÍ
A37: Cumple aval o seguro | B37: =IF(OR(Solicitud!B43="Sí",Solicitud!B44="Sí"),"SÍ","NO") -> NO
A39: 5) DICTAMEN
A40: Dictamen del analista | D40: Escriba conclusiones y condiciones.
A41: Recomendación final | B41: =IF(AND(B34="SÍ",B35="SÍ",B36="SÍ",B37="SÍ"),"APROBABLE","REVISAR / CONDICIONAR") -> #NUM!

Sheet Amortización
A1: TABLA DE AMORTIZACIÓN – PRÉSTAMO FIDUCIARIO
A3: CLIENTE: | C3: =Solicitud!B16 -> 0
A4: Gastos Operativos | C4: 0.03 | D4: =SUM(C12*C4) -> 0
A5: Aportaciones | C5: 0.05 | D5: =SUM(C12*C5) -> 0
A6: Tasa de Seguridad
A7: Cancelación Préstamo | D7: 0
A8: Total deducciones | D8: =SUM(D4:D7) -> 0
A9: Total a desembolsar | D9: =SUM(C12-D8) -> 0 | E9: FECHAS: | F9: Inicio | G9: Final
C11: MONTO | D11: PLAZO | E11: TASA | F11: CUOTA | G11: Cuota+Aport
B12: Principal | C12: =Solicitud!B35 -> 0 | D12: =Solicitud!B36 -> 0 | E12: ='Análisis de Crédito'!B5 -> 0.18 | F12: =C12/((1-((1+(E12/12))^-D12))/(E12/12)) -> #DIV/0! | G12: =F12+Solicitud!B45 -> #DIV/0!
B13: Plazo (meses)
B14: Tasa anual
B15: Cuota (fórmula)
B16: Fecha 1er pago (opcional) | C16: =Solicitud!B40 -> 0
A18: # | B18: Fecha | C18: Saldo inicial | D18: Cuota | E18: Interés | F18: Capital | G18: Saldo final
A19: =IF(1<=$D$12,1,"") | B19: =IF(1<=$D$12,IF($C$16="","",EDATE($C$16,1-1)),"") | C19: =IF(1<=$D$12,$C$12,"") | D19: =IF(1<=$D$12,$F$12,"") | E19: =IF(1<=$D$12,C19*($E$12/12),"") | F19: =IF(1<=$D$12,D19-E19,"") | G19: =IF(1<=$D$12,MAX(0,C19-F19),"")
A20: =IF(2<=$D$12,2,"") | B20: =IF(2<=$D$12,IF($C$16="","",EDATE($C$16,2-1)),"") | C20: =IF(2<=$D$12,G19,"") | D20: =IF(1<=$D$12,$F$12,"") | E20: =IF(1<=$D$12,C20*($E$12/12),"") | F20: =IF(2<=$D$12,D20-E20,"") | G20: =IF(2<=$D$12,MAX(0,C20-F20),"")
A21: =IF(3<=$D$12,3,"") | B21: =IF(3<=$D$12,IF($C$16="","",EDATE($C$16,3-1)),"") | C21: =IF(3<=$D$12,G20,"") | D21: =IF(1<=$D$12,$F$12,"") | E21: =IF(1<=$D$12,C21*($E$12/12),"") | F21: =IF(3<=$D$12,D21-E21,"") | G21: =IF(3<=$D$12,MAX(0,C21-F21),"")
A22: =IF(4<=$D$12,4,"") | B22: =IF(4<=$D$12,IF($C$16="","",EDATE($C$16,4-1)),"") | C22: =IF(4<=$D$12,G21,"") | D22: =IF(1<=$D$12,$F$12,"") | E22: =IF(1<=$D$12,C22*($E$12/12),"") | F22: =IF(4<=$D$12,D22-E22,"") | G22: =IF(4<=$D$12,MAX(0,C22-F22),"")
A23: =IF(5<=$D$12,5,"") | B23: =IF(5<=$D$12,IF($C$16="","",EDATE($C$16,5-1)),"") | C23: =IF(5<=$D$12,G22,"") | D23: =IF(1<=$D$12,$F$12,"") | E23: =IF(1<=$D$12,C23*($E$12/12),"") | F23: =IF(5<=$D$12,D23-E23,"") | G23: =IF(5<=$D$12,MAX(0,C23-F23),"")
A24: =IF(6<=$D$12,6,"") | B24: =IF(6<=$D$12,IF($C$16="","",EDATE($C$16,6-1)),"") | C24: =IF(6<=$D$12,G23,"") | D24: =IF(1<=$D$12,$F$12,"") | E24: =IF(1<=$D$12,C24*($E$12/12),"") | F24: =IF(6<=$D$12,D24-E24,"") | G24: =IF(6<=$D$12,MAX(0,C24-F24),"")
A25: =IF(7<=$D$12,7,"") | B25: =IF(7<=$D$12,IF($C$16="","",EDATE($C$16,7-1)),"") | C25: =IF(7<=$D$12,G24,"") | D25: =IF(1<=$D$12,$F$12,"") | E25: =IF(1<=$D$12,C25*($E$12/12),"") | F25: =IF(7<=$D$12,D25-E25,"") | G25: =IF(7<=$D$12,MAX(0,C25-F25),"")
A26: =IF(8<=$D$12,8,"") | B26: =IF(8<=$D$12,IF($C$16="","",EDATE($C$16,8-1)),"") | C26: =IF(8<=$D$12,G25,"") | D26: =IF(1<=$D$12,$F$12,"") | E26: =IF(1<=$D$12,C26*($E$12/12),"") | F26: =IF(8<=$D$12,D26-E26,"") | G26: =IF(8<=$D$12,MAX(0,C26-F26),"")
A27: =IF(9<=$D$12,9,"") | B27: =IF(9<=$D$12,IF($C$16="","",EDATE($C$16,9-1)),"") | C27: =IF(9<=$D$12,G26,"") | D27: =IF(1<=$D$12,$F$12,"") | E27: =IF(1<=$D$12,C27*($E$12/12),"") | F27: =IF(9<=$D$12,D27-E27,"") | G27: =IF(9<=$D$12,MAX(0,C27-F27),"")
A28: =IF(10<=$D$12,10,"") | B28: =IF(10<=$D$12,IF($C$16="","",EDATE($C$16,10-1)),"") | C28: =IF(10<=$D$12,G27,"") | D28: =IF(1<=$D$12,$F$12,"") | E28: =IF(1<=$D$12,C28*($E$12/12),"") | F28: =IF(10<=$D$12,D28-E28,"") | G28: =IF(10<=$D$12,MAX(0,C28-F28),"")
A29: =IF(11<=$D$12,11,"") | B29: =IF(11<=$D$12,IF($C$16="","",EDATE($C$16,11-1)),"") | C29: =IF(11<=$D$12,G28,"") | D29: =IF(1<=$D$12,$F$12,"") | E29: =IF(1<=$D$12,C29*($E$12/12),"") | F29: =IF(11<=$D$12,D29-E29,"") | G29: =IF(11<=$D$12,MAX(0,C29-F29),"")
A30: =IF(12<=$D$12,12,"") | B30: =IF(12<=$D$12,IF($C$16="","",EDATE($C$16,12-1)),"") | C30: =IF(12<=$D$12,G29,"") | D30: =IF(1<=$D$12,$F$12,"") | E30: =IF(1<=$D$12,C30*($E$12/12),"") | F30: =IF(12<=$D$12,D30-E30,"") | G30: =IF(12<=$D$12,MAX(0,C30-F30),"")
A31: =IF(13<=$D$12,13,"") | B31: =IF(13<=$D$12,IF($C$16="","",EDATE($C$16,13-1)),"") | C31: =IF(13<=$D$12,G30,"") | D31: =IF(1<=$D$12,$F$12,"") | E31: =IF(1<=$D$12,C31*($E$12/12),"") | F31: =IF(13<=$D$12,D31-E31,"") | G31: =IF(13<=$D$12,MAX(0,C31-F31),"")
A32: =IF(14<=$D$12,14,"") | B32: =IF(14<=$D$12,IF($C$16="","",EDATE($C$16,14-1)),"") | C32: =IF(14<=$D$12,G31,"") | D32: =IF(1<=$D$12,$F$12,"") | E32: =IF(1<=$D$12,C32*($E$12/12),"") | F32: =IF(14<=$D$12,D32-E32,"") | G32: =IF(14<=$D$12,MAX(0,C32-F32),"")
A33: =IF(15<=$D$12,15,"") | B33: =IF(15<=$D$12,IF($C$16="","",EDATE($C$16,15-1)),"") | C33: =IF(15<=$D$12,G32,"") | D33: =IF(1<=$D$12,$F$12,"") | E33: =IF(1<=$D$12,C33*($E$12/12),"") | F33: =IF(15<=$D$12,D33-E33,"") | G33: =IF(15<=$D$12,MAX(0,C33-F33),"")
A34: =IF(16<=$D$12,16,"") | B34: =IF(16<=$D$12,IF($C$16="","",EDATE($C$16,16-1)),"") | C34: =IF(16<=$D$12,G33,"") | D34: =IF(1<=$D$12,$F$12,"") | E34: =IF(1<=$D$12,C34*($E$12/12),"") | F34: =IF(16<=$D$12,D34-E34,"") | G34: =IF(16<=$D$12,MAX(0,C34-F34),"")
A35: =IF(17<=$D$12,17,"") | B35: =IF(17<=$D$12,IF($C$16="","",EDATE($C$16,17-1)),"") | C35: =IF(17<=$D$12,G34,"") | D35: =IF(1<=$D$12,$F$12,"") | E35: =IF(1<=$D$12,C35*($E$12/12),"") | F35: =IF(17<=$D$12,D35-E35,"") | G35: =IF(17<=$D$12,MAX(0,C35-F35),"")
A36: =IF(18<=$D$12,18,"") | B36: =IF(18<=$D$12,IF($C$16="","",EDATE($C$16,18-1)),"") | C36: =IF(18<=$D$12,G35,"") | D36: =IF(1<=$D$12,$F$12,"") | E36: =IF(1<=$D$12,C36*($E$12/12),"") | F36: =IF(18<=$D$12,D36-E36,"") | G36: =IF(18<=$D$12,MAX(0,C36-F36),"")
A37: =IF(19<=$D$12,19,"") | B37: =IF(19<=$D$12,IF($C$16="","",EDATE($C$16,19-1)),"") | C37: =IF(19<=$D$12,G36,"") | D37: =IF(1<=$D$12,$F$12,"") | E37: =IF(1<=$D$12,C37*($E$12/12),"") | F37: =IF(19<=$D$12,D37-E37,"") | G37: =IF(19<=$D$12,MAX(0,C37-F37),"")
A38: =IF(20<=$D$12,20,"") | B38: =IF(20<=$D$12,IF($C$16="","",EDATE($C$16,20-1)),"") | C38: =IF(20<=$D$12,G37,"") | D38: =IF(1<=$D$12,$F$12,"") | E38: =IF(1<=$D$12,C38*($E$12/12),"") | F38: =IF(20<=$D$12,D38-E38,"") | G38: =IF(20<=$D$12,MAX(0,C38-F38),"")
A39: =IF(21<=$D$12,21,"") | B39: =IF(21<=$D$12,IF($C$16="","",EDATE($C$16,21-1)),"") | C39: =IF(21<=$D$12,G38,"") | D39: =IF(1<=$D$12,$F$12,"") | E39: =IF(1<=$D$12,C39*($E$12/12),"") | F39: =IF(21<=$D$12,D39-E39,"") | G39: =IF(21<=$D$12,MAX(0,C39-F39),"")
A40: =IF(22<=$D$12,22,"") | B40: =IF(22<=$D$12,IF($C$16="","",EDATE($C$16,22-1)),"") | C40: =IF(22<=$D$12,G39,"") | D40: =IF(1<=$D$12,$F$12,"") | E40: =IF(1<=$D$12,C40*($E$12/12),"") | F40: =IF(22<=$D$12,D40-E40,"") | G40: =IF(22<=$D$12,MAX(0,C40-F40),"")
A41: =IF(23<=$D$12,23,"") | B41: =IF(23<=$D$12,IF($C$16="","",EDATE($C$16,23-1)),"") | C41: =IF(23<=$D$12,G40,"") | D41: =IF(1<=$D$12,$F$12,"") | E41: =IF(1<=$D$12,C41*($E$12/12),"") | F41: =IF(23<=$D$12,D41-E41,"") | G41: =IF(23<=$D$12,MAX(0,C41-F41),"")
A42: =IF(24<=$D$12,24,"") | B42: =IF(24<=$D$12,IF($C$16="","",EDATE($C$16,24-1)),"") | C42: =IF(24<=$D$12,G41,"") | D42: =IF(1<=$D$12,$F$12,"") | E42: =IF(1<=$D$12,C42*($E$12/12),"") | F42: =IF(24<=$D$12,D42-E42,"") | G42: =IF(24<=$D$12,MAX(0,C42-F42),"")
A43: =IF(25<=$D$12,25,"") | B43: =IF(25<=$D$12,IF($C$16="","",EDATE($C$16,25-1)),"") | C43: =IF(25<=$D$12,G42,"") | D43: =IF(1<=$D$12,$F$12,"") | E43: =IF(1<=$D$12,C43*($E$12/12),"") | F43: =IF(25<=$D$12,D43-E43,"") | G43: =IF(25<=$D$12,MAX(0,C43-F43),"")
A44: =IF(26<=$D$12,26,"") | B44: =IF(26<=$D$12,IF($C$16="","",EDATE($C$16,26-1)),"") | C44: =IF(26<=$D$12,G43,"") | D44: =IF(1<=$D$12,$F$12,"") | E44: =IF(1<=$D$12,C44*($E$12/12),"") | F44: =IF(26<=$D$12,D44-E44,"") | G44: =IF(26<=$D$12,MAX(0,C44-F44),"")
A45: =IF(27<=$D$12,27,"") | B45: =IF(27<=$D$12,IF($C$16="","",EDATE($C$16,27-1)),"") | C45: =IF(27<=$D$12,G44,"") | D45: =IF(1<=$D$12,$F$12,"") | E45: =IF(1<=$D$12,C45*($E$12/12),"") | F45: =IF(27<=$D$12,D45-E45,"") | G45: =IF(27<=$D$12,MAX(0,C45-F45),"")
A46: =IF(28<=$D$12,28,"") | B46: =IF(28<=$D$12,IF($C$16="","",EDATE($C$16,28-1)),"") | C46: =IF(28<=$D$12,G45,"") | D46: =IF(1<=$D$12,$F$12,"") | E46: =IF(1<=$D$12,C46*($E$12/12),"") | F46: =IF(28<=$D$12,D46-E46,"") | G46: =IF(28<=$D$12,MAX(0,C46-F46),"")
A47: =IF(29<=$D$12,29,"") | B47: =IF(29<=$D$12,IF($C$16="","",EDATE($C$16,29-1)),"") | C47: =IF(29<=$D$12,G46,"") | D47: =IF(1<=$D$12,$F$12,"") | E47: =IF(1<=$D$12,C47*($E$12/12),"") | F47: =IF(29<=$D$12,D47-E47,"") | G47: =IF(29<=$D$12,MAX(0,C47-F47),"")
A48: =IF(30<=$D$12,30,"") | B48: =IF(30<=$D$12,IF($C$16="","",EDATE($C$16,30-1)),"") | C48: =IF(30<=$D$12,G47,"") | D48: =IF(1<=$D$12,$F$12,"") | E48: =IF(1<=$D$12,C48*($E$12/12),"") | F48: =IF(30<=$D$12,D48-E48,"") | G48: =IF(30<=$D$12,MAX(0,C48-F48),"")
A49: =IF(31<=$D$12,31,"") | B49: =IF(31<=$D$12,IF($C$16="","",EDATE($C$16,31-1)),"") | C49: =IF(31<=$D$12,G48,"") | D49: =IF(1<=$D$12,$F$12,"") | E49: =IF(1<=$D$12,C49*($E$12/12),"") | F49: =IF(31<=$D$12,D49-E49,"") | G49: =IF(31<=$D$12,MAX(0,C49-F49),"")
A50: =IF(32<=$D$12,32,"") | B50: =IF(32<=$D$12,IF($C$16="","",EDATE($C$16,32-1)),"") | C50: =IF(32<=$D$12,G49,"") | D50: =IF(1<=$D$12,$F$12,"") | E50: =IF(1<=$D$12,C50*($E$12/12),"") | F50: =IF(32<=$D$12,D50-E50,"") | G50: =IF(32<=$D$12,MAX(0,C50-F50),"")
A51: =IF(33<=$D$12,33,"") | B51: =IF(33<=$D$12,IF($C$16="","",EDATE($C$16,33-1)),"") | C51: =IF(33<=$D$12,G50,"") | D51: =IF(1<=$D$12,$F$12,"") | E51: =IF(1<=$D$12,C51*($E$12/12),"") | F51: =IF(33<=$D$12,D51-E51,"") | G51: =IF(33<=$D$12,MAX(0,C51-F51),"")
A52: =IF(34<=$D$12,34,"") | B52: =IF(34<=$D$12,IF($C$16="","",EDATE($C$16,34-1)),"") | C52: =IF(34<=$D$12,G51,"") | D52: =IF(1<=$D$12,$F$12,"") | E52: =IF(1<=$D$12,C52*($E$12/12),"") | F52: =IF(34<=$D$12,D52-E52,"") | G52: =IF(34<=$D$12,MAX(0,C52-F52),"")
A53: =IF(35<=$D$12,35,"") | B53: =IF(35<=$D$12,IF($C$16="","",EDATE($C$16,35-1)),"") | C53: =IF(35<=$D$12,G52,"") | D53: =IF(1<=$D$12,$F$12,"") | E53: =IF(1<=$D$12,C53*($E$12/12),"") | F53: =IF(35<=$D$12,D53-E53,"") | G53: =IF(35<=$D$12,MAX(0,C53-F53),"")
A54: =IF(36<=$D$12,36,"") | B54: =IF(36<=$D$12,IF($C$16="","",EDATE($C$16,36-1)),"") | C54: =IF(36<=$D$12,G53,"") | D54: =IF(1<=$D$12,$F$12,"") | E54: =IF(1<=$D$12,C54*($E$12/12),"") | F54: =IF(36<=$D$12,D54-E54,"") | G54: =IF(36<=$D$12,MAX(0,C54-F54),"")
A55: =IF(37<=$D$12,37,"") | B55: =IF(37<=$D$12,IF($C$16="","",EDATE($C$16,37-1)),"") | C55: =IF(37<=$D$12,G54,"") | D55: =IF(37<=$D$12,$F$12,"") | E55: =IF(37<=$D$12,C55*($E$12/12),"") | F55: =IF(37<=$D$12,D55-E55,"") | G55: =IF(37<=$D$12,MAX(0,C55-F55),"")
A56: =IF(38<=$D$12,38,"") | B56: =IF(38<=$D$12,IF($C$16="","",EDATE($C$16,38-1)),"") | C56: =IF(38<=$D$12,G55,"") | D56: =IF(38<=$D$12,$F$12,"") | E56: =IF(38<=$D$12,C56*($E$12/12),"") | F56: =IF(38<=$D$12,D56-E56,"") | G56: =IF(38<=$D$12,MAX(0,C56-F56),"")
A57: =IF(39<=$D$12,39,"") | B57: =IF(39<=$D$12,IF($C$16="","",EDATE($C$16,39-1)),"") | C57: =IF(39<=$D$12,G56,"") | D57: =IF(39<=$D$12,$F$12,"") | E57: =IF(39<=$D$12,C57*($E$12/12),"") | F57: =IF(39<=$D$12,D57-E57,"") | G57: =IF(39<=$D$12,MAX(0,C57-F57),"")
A58: =IF(40<=$D$12,40,"") | B58: =IF(40<=$D$12,IF($C$16="","",EDATE($C$16,40-1)),"") | C58: =IF(40<=$D$12,G57,"") | D58: =IF(40<=$D$12,$F$12,"") | E58: =IF(40<=$D$12,C58*($E$12/12),"") | F58: =IF(40<=$D$12,D58-E58,"") | G58: =IF(40<=$D$12,MAX(0,C58-F58),"")
A59: =IF(41<=$D$12,41,"") | B59: =IF(41<=$D$12,IF($C$16="","",EDATE($C$16,41-1)),"") | C59: =IF(41<=$D$12,G58,"") | D59: =IF(41<=$D$12,$F$12,"") | E59: =IF(41<=$D$12,C59*($E$12/12),"") | F59: =IF(41<=$D$12,D59-E59,"") | G59: =IF(41<=$D$12,MAX(0,C59-F59),"")
A60: =IF(42<=$D$12,42,"") | B60: =IF(42<=$D$12,IF($C$16="","",EDATE($C$16,42-1)),"") | C60: =IF(42<=$D$12,G59,"") | D60: =IF(42<=$D$12,$F$12,"") | E60: =IF(42<=$D$12,C60*($E$12/12),"") | F60: =IF(42<=$D$12,D60-E60,"") | G60: =IF(42<=$D$12,MAX(0,C60-F60),"")
A61: =IF(43<=$D$12,43,"") | B61: =IF(43<=$D$12,IF($C$16="","",EDATE($C$16,43-1)),"") | C61: =IF(43<=$D$12,G60,"") | D61: =IF(43<=$D$12,$F$12,"") | E61: =IF(43<=$D$12,C61*($E$12/12),"") | F61: =IF(43<=$D$12,D61-E61,"") | G61: =IF(43<=$D$12,MAX(0,C61-F61),"")
A62: =IF(44<=$D$12,44,"") | B62: =IF(44<=$D$12,IF($C$16="","",EDATE($C$16,44-1)),"") | C62: =IF(44<=$D$12,G61,"") | D62: =IF(44<=$D$12,$F$12,"") | E62: =IF(44<=$D$12,C62*($E$12/12),"") | F62: =IF(44<=$D$12,D62-E62,"") | G62: =IF(44<=$D$12,MAX(0,C62-F62),"")
A63: =IF(45<=$D$12,45,"") | B63: =IF(45<=$D$12,IF($C$16="","",EDATE($C$16,45-1)),"") | C63: =IF(45<=$D$12,G62,"") | D63: =IF(45<=$D$12,$F$12,"") | E63: =IF(45<=$D$12,C63*($E$12/12),"") | F63: =IF(45<=$D$12,D63-E63,"") | G63: =IF(45<=$D$12,MAX(0,C63-F63),"")
A64: =IF(46<=$D$12,46,"") | B64: =IF(46<=$D$12,IF($C$16="","",EDATE($C$16,46-1)),"") | C64: =IF(46<=$D$12,G63,"") | D64: =IF(46<=$D$12,$F$12,"") | E64: =IF(46<=$D$12,C64*($E$12/12),"") | F64: =IF(46<=$D$12,D64-E64,"") | G64: =IF(46<=$D$12,MAX(0,C64-F64),"")
A65: =IF(47<=$D$12,47,"") | B65: =IF(47<=$D$12,IF($C$16="","",EDATE($C$16,47-1)),"") | C65: =IF(47<=$D$12,G64,"") | D65: =IF(47<=$D$12,$F$12,"") | E65: =IF(47<=$D$12,C65*($E$12/12),"") | F65: =IF(47<=$D$12,D65-E65,"") | G65: =IF(47<=$D$12,MAX(0,C65-F65),"")
A66: =IF(48<=$D$12,48,"") | B66: =IF(48<=$D$12,IF($C$16="","",EDATE($C$16,48-1)),"") | C66: =IF(48<=$D$12,G65,"") | D66: =IF(48<=$D$12,$F$12,"") | E66: =IF(48<=$D$12,C66*($E$12/12),"") | F66: =IF(48<=$D$12,D66-E66,"") | G66: =IF(48<=$D$12,MAX(0,C66-F66),"")
A67: =IF(49<=$D$12,49,"") | B67: =IF(49<=$D$12,IF($C$16="","",EDATE($C$16,49-1)),"") | C67: =IF(49<=$D$12,G66,"") | D67: =IF(49<=$D$12,$F$12,"") | E67: =IF(49<=$D$12,C67*($E$12/12),"") | F67: =IF(49<=$D$12,D67-E67,"") | G67: =IF(49<=$D$12,MAX(0,C67-F67),"")
A68: =IF(50<=$D$12,50,"") | B68: =IF(50<=$D$12,IF($C$16="","",EDATE($C$16,50-1)),"") | C68: =IF(50<=$D$12,G67,"") | D68: =IF(50<=$D$12,$F$12,"") | E68: =IF(50<=$D$12,C68*($E$12/12),"") | F68: =IF(50<=$D$12,D68-E68,"") | G68: =IF(50<=$D$12,MAX(0,C68-F68),"")
A69: =IF(51<=$D$12,51,"") | B69: =IF(51<=$D$12,IF($C$16="","",EDATE($C$16,51-1)),"") | C69: =IF(51<=$D$12,G68,"") | D69: =IF(51<=$D$12,$F$12,"") | E69: =IF(51<=$D$12,C69*($E$12/12),"") | F69: =IF(51<=$D$12,D69-E69,"") | G69: =IF(51<=$D$12,MAX(0,C69-F69),"")
A70: =IF(52<=$D$12,52,"") | B70: =IF(52<=$D$12,IF($C$16="","",EDATE($C$16,52-1)),"") | C70: =IF(52<=$D$12,G69,"") | D70: =IF(52<=$D$12,$F$12,"") | E70: =IF(52<=$D$12,C70*($E$12/12),"") | F70: =IF(52<=$D$12,D70-E70,"") | G70: =IF(52<=$D$12,MAX(0,C70-F70),"")
A71: =IF(53<=$D$12,53,"") | B71: =IF(53<=$D$12,IF($C$16="","",EDATE($C$16,53-1)),"") | C71: =IF(53<=$D$12,G70,"") | D71: =IF(53<=$D$12,$F$12,"") | E71: =IF(53<=$D$12,C71*($E$12/12),"") | F71: =IF(53<=$D$12,D71-E71,"") | G71: =IF(53<=$D$12,MAX(0,C71-F71),"")
A72: =IF(54<=$D$12,54,"") | B72: =IF(54<=$D$12,IF($C$16="","",EDATE($C$16,54-1)),"") | C72: =IF(54<=$D$12,G71,"") | D72: =IF(54<=$D$12,$F$12,"") | E72: =IF(54<=$D$12,C72*($E$12/12),"") | F72: =IF(54<=$D$12,D72-E72,"") | G72: =IF(54<=$D$12,MAX(0,C72-F72),"")
A73: =IF(55<=$D$12,55,"") | B73: =IF(55<=$D$12,IF($C$16="","",EDATE($C$16,55-1)),"") | C73: =IF(55<=$D$12,G72,"") | D73: =IF(55<=$D$12,$F$12,"") | E73: =IF(55<=$D$12,C73*($E$12/12),"") | F73: =IF(55<=$D$12,D73-E73,"") | G73: =IF(55<=$D$12,MAX(0,C73-F73),"")
A74: =IF(56<=$D$12,56,"") | B74: =IF(56<=$D$12,IF($C$16="","",EDATE($C$16,56-1)),"") | C74: =IF(56<=$D$12,G73,"") | D74: =IF(56<=$D$12,$F$12,"") | E74: =IF(56<=$D$12,C74*($E$12/12),"") | F74: =IF(56<=$D$12,D74-E74,"") | G74: =IF(56<=$D$12,MAX(0,C74-F74),"")
A75: =IF(57<=$D$12,57,"") | B75: =IF(57<=$D$12,IF($C$16="","",EDATE($C$16,57-1)),"") | C75: =IF(57<=$D$12,G74,"") | D75: =IF(57<=$D$12,$F$12,"") | E75: =IF(57<=$D$12,C75*($E$12/12),"") | F75: =IF(57<=$D$12,D75-E75,"") | G75: =IF(57<=$D$12,MAX(0,C75-F75),"")
A76: =IF(58<=$D$12,58,"") | B76: =IF(58<=$D$12,IF($C$16="","",EDATE($C$16,58-1)),"") | C76: =IF(58<=$D$12,G75,"") | D76: =IF(58<=$D$12,$F$12,"") | E76: =IF(58<=$D$12,C76*($E$12/12),"") | F76: =IF(58<=$D$12,D76-E76,"") | G76: =IF(58<=$D$12,MAX(0,C76-F76),"")
A77: =IF(59<=$D$12,59,"") | B77: =IF(59<=$D$12,IF($C$16="","",EDATE($C$16,59-1)),"") | C77: =IF(59<=$D$12,G76,"") | D77: =IF(59<=$D$12,$F$12,"") | E77: =IF(59<=$D$12,C77*($E$12/12),"") | F77: =IF(59<=$D$12,D77-E77,"") | G77: =IF(59<=$D$12,MAX(0,C77-F77),"")
A78: =IF(60<=$D$12,60,"") | B78: =IF(60<=$D$12,IF($C$16="","",EDATE($C$16,60-1)),"") | C78: =IF(60<=$D$12,G77,"") | D78: =IF(60<=$D$12,$F$12,"") | E78: =IF(60<=$D$12,C78*($E$12/12),"") | F78: =IF(60<=$D$12,D78-E78,"") | G78: =IF(60<=$D$12,MAX(0,C78-F78),"")
A79: =IF(61<=$D$12,61,"") | B79: =IF(61<=$D$12,IF($C$16="","",EDATE($C$16,61-1)),"") | C79: =IF(61<=$D$12,G78,"") | D79: =IF(61<=$D$12,$F$12,"") | E79: =IF(61<=$D$12,C79*($E$12/12),"") | F79: =IF(61<=$D$12,D79-E79,"") | G79: =IF(61<=$D$12,MAX(0,C79-F79),"")
A80: =IF(62<=$D$12,62,"") | B80: =IF(62<=$D$12,IF($C$16="","",EDATE($C$16,62-1)),"") | C80: =IF(62<=$D$12,G79,"") | D80: =IF(62<=$D$12,$F$12,"") | E80: =IF(62<=$D$12,C80*($E$12/12),"") | F80: =IF(62<=$D$12,D80-E80,"") | G80: =IF(62<=$D$12,MAX(0,C80-F80),"")
A81: =IF(63<=$D$12,63,"") | B81: =IF(63<=$D$12,IF($C$16="","",EDATE($C$16,63-1)),"") | C81: =IF(63<=$D$12,G80,"") | D81: =IF(63<=$D$12,$F$12,"") | E81: =IF(63<=$D$12,C81*($E$12/12),"") | F81: =IF(63<=$D$12,D81-E81,"") | G81: =IF(63<=$D$12,MAX(0,C81-F81),"")
A82: =IF(64<=$D$12,64,"") | B82: =IF(64<=$D$12,IF($C$16="","",EDATE($C$16,64-1)),"") | C82: =IF(64<=$D$12,G81,"") | D82: =IF(64<=$D$12,$F$12,"") | E82: =IF(64<=$D$12,C82*($E$12/12),"") | F82: =IF(64<=$D$12,D82-E82,"") | G82: =IF(64<=$D$12,MAX(0,C82-F82),"")
A83: =IF(65<=$D$12,65,"") | B83: =IF(65<=$D$12,IF($C$16="","",EDATE($C$16,65-1)),"") | C83: =IF(65<=$D$12,G82,"") | D83: =IF(65<=$D$12,$F$12,"") | E83: =IF(65<=$D$12,C83*($E$12/12),"") | F83: =IF(65<=$D$12,D83-E83,"") | G83: =IF(65<=$D$12,MAX(0,C83-F83),"")
A84: =IF(66<=$D$12,66,"") | B84: =IF(66<=$D$12,IF($C$16="","",EDATE($C$16,66-1)),"") | C84: =IF(66<=$D$12,G83,"") | D84: =IF(66<=$D$12,$F$12,"") | E84: =IF(66<=$D$12,C84*($E$12/12),"") | F84: =IF(66<=$D$12,D84-E84,"") | G84: =IF(66<=$D$12,MAX(0,C84-F84),"")
A85: =IF(67<=$D$12,67,"") | B85: =IF(67<=$D$12,IF($C$16="","",EDATE($C$16,67-1)),"") | C85: =IF(67<=$D$12,G84,"") | D85: =IF(67<=$D$12,$F$12,"") | E85: =IF(67<=$D$12,C85*($E$12/12),"") | F85: =IF(67<=$D$12,D85-E85,"") | G85: =IF(67<=$D$12,MAX(0,C85-F85),"")
A86: =IF(68<=$D$12,68,"") | B86: =IF(68<=$D$12,IF($C$16="","",EDATE($C$16,68-1)),"") | C86: =IF(68<=$D$12,G85,"") | D86: =IF(68<=$D$12,$F$12,"") | E86: =IF(68<=$D$12,C86*($E$12/12),"") | F86: =IF(68<=$D$12,D86-E86,"") | G86: =IF(68<=$D$12,MAX(0,C86-F86),"")
A87: =IF(69<=$D$12,69,"") | B87: =IF(69<=$D$12,IF($C$16="","",EDATE($C$16,69-1)),"") | C87: =IF(69<=$D$12,G86,"") | D87: =IF(69<=$D$12,$F$12,"") | E87: =IF(69<=$D$12,C87*($E$12/12),"") | F87: =IF(69<=$D$12,D87-E87,"") | G87: =IF(69<=$D$12,MAX(0,C87-F87),"")
A88: =IF(70<=$D$12,70,"") | B88: =IF(70<=$D$12,IF($C$16="","",EDATE($C$16,70-1)),"") | C88: =IF(70<=$D$12,G87,"") | D88: =IF(70<=$D$12,$F$12,"") | E88: =IF(70<=$D$12,C88*($E$12/12),"") | F88: =IF(70<=$D$12,D88-E88,"") | G88: =IF(70<=$D$12,MAX(0,C88-F88),"")
A89: =IF(71<=$D$12,71,"") | B89: =IF(71<=$D$12,IF($C$16="","",EDATE($C$16,71-1)),"") | C89: =IF(71<=$D$12,G88,"") | D89: =IF(71<=$D$12,$F$12,"") | E89: =IF(71<=$D$12,C89*($E$12/12),"") | F89: =IF(71<=$D$12,D89-E89,"") | G89: =IF(71<=$D$12,MAX(0,C89-F89),"")
A90: =IF(72<=$D$12,72,"") | B90: =IF(72<=$D$12,IF($C$16="","",EDATE($C$16,72-1)),"") | C90: =IF(72<=$D$12,G89,"") | D90: =IF(72<=$D$12,$F$12,"") | E90: =IF(72<=$D$12,C90*($E$12/12),"") | F90: =IF(72<=$D$12,D90-E90,"") | G90: =IF(72<=$D$12,MAX(0,C90-F90),"")
